Workbook

Sheet Transaction Summary
A2: September Transaction Summary | C2: K
A4: Savings | C4: =Declarations!C173 -> 28000
A5: Loan Repayments | C5: =SUM(Declarations!D173:J173) -> 36420
A6: Penalty | C6: =Declarations!H94 -> 0
A8: Cash Available for Loans | C8: =SUM(C4:C7) -> 64420
A10: Birthdays | C10: =Declarations!J132 -> 1200
A11: Admin Fee | C11: =Declarations!K132 -> 650
A13: Total Cash collected | C13: =SUM(C8:C11) -> 66270
A16: Loans disbursed in august | C16: ='Loans disbursed'!K18 -> 64420
A18: Total Savings | C18: =Savings!O18 -> 300350
A19: Total Interest | C19: ='Total Interest earned'!O19 -> 82517.513
A20: Total penalties | C20: ='Penalty interest'!M18 -> 690
A21: Total Savings and Interest | C21: =SUM(C18:C20) -> 383557.51
A24: Total Outstanding Loans | C24: ='Loan statements'!G197 -> 383557.51
A26: Cash at Bank | C26: =C8-C16 -> 0

Sheet Summary
A1: Social Shreholders Summary
A2: 45870
A3: 7 | B3: Members Name | C3: Total Savings | D3: Total Interest earned | E3: Penalties | F3: Total Savings plus interest | G3: Loans | H3: Net Position
A4: 1 | B4: Aibaki Tembo | C4: =Savings!O4 -> 14900 | D4: ='Total Interest earned'!O5 -> 3871.7247 | E4: ='Penalty interest'!M4 -> 53.076923 | F4: =C4+D4+E4 -> 18824.802 | G4: ='Loan statements'!G177 -> 10833 | H4: =F4-G4 -> 7991.8016
A5: 2 | B5: Brian Chirwa | C5: =Savings!O5 -> 16000 | D5: ='Total Interest earned'!O6 -> 4651.4 | E5: ='Penalty interest'!M5 -> 53.076923 | F5: =C5+D5+E5 -> 20704.477 | G5: ='Loan statements'!G178+'Loan statements'!G179 -> 9900 | H5: =F5-G5 -> 10804.477
A6: 3 | B6: Chilu Nyendwa | C6: =Savings!O6 -> 23100 | D6: ='Total Interest earned'!O7 -> 6959.0845 | E6: ='Penalty interest'!M6 -> 53.076923 | F6: =C6+D6+E6 -> 30112.161 | G6: ='Loan statements'!G180+'Loan statements'!G181 -> 51073.75 | H6: =F6-G6 -> -20961.589
A7: 4 | B7: Clive Makala | C7: =Savings!O7 -> 26500 | D7: ='Total Interest earned'!O8 -> 8195.8823 | E7: ='Penalty interest'!M7 -> 53.076923 | F7: =C7+D7+E7 -> 34748.959 | G7: ='Loan statements'!G182+'Loan statements'!G183 -> 73130.762 | H7: =F7-G7 -> -38381.803
A8: 5 | B8: David Machungwa | C8: =Savings!O8 -> 51350 | D8: ='Total Interest earned'!O9 -> 11041.001 | E8: ='Penalty interest'!M8 -> 53.076923 | F8: =C8+D8+E8 -> 62444.078 | G8: ='Loan statements'!G184 -> 56000 | H8: =F8-G8 -> 6444.078
A9: 6 | B9: Kababa Kangwa | C9: =Savings!O9 -> 37000 | D9: ='Total Interest earned'!O10 -> 10051.655 | E9: ='Penalty interest'!M9 -> 53.076923 | F9: =C9+D9+E9 -> 47104.732 | G9: ='Loan statements'!G185 -> 13565 | H9: =F9-G9 -> 33539.732
A10: 7 | B10: Kalenga Kamwendo | C10: =Savings!O10 -> 8300 | D10: ='Total Interest earned'!O11 -> 2648.2523 | E10: ='Penalty interest'!M10 -> 53.076923 | F10: =C10+D10+E10 -> 11001.329 | G10: ='Loan statements'!G186 -> 57500 | H10: =F10-G10 -> -46498.671
A11: 8 | B11: Kote Nikoi | C11: =Savings!O11 -> 15100 | D11: ='Total Interest earned'!O12 -> 4741.9977 | E11: ='Penalty interest'!M11 -> 53.076923 | F11: =C11+D11+E11 -> 19895.075 | G11: ='Loan statements'!G187+'Loan statements'!G188 -> 13900 | H11: =F11-G11 -> 5995.0746
A12: 9 | B12: Kunda Maliti | C12: =Savings!O12 -> 28400 | D12: ='Total Interest earned'!O13 -> 7715.8579 | E12: ='Penalty interest'!M12 -> 53.076923 | F12: =C12+D12+E12 -> 36168.935 | G12: ='Loan statements'!G189 -> 32300 | H12: =F12-G12 -> 3868.9348
A13: 10 | B13: Mapenzi Mweetwa | C13: =Savings!O13 -> 24350 | D13: ='Total Interest earned'!O14 -> 6662.5013 | E13: ='Penalty interest'!M13 -> 53.076923 | F13: =C13+D13+E13 -> 31065.578 | G13: ='Loan statements'!G190+'Loan statements'!G191+'Loan statements'!G192 -> 40005 | H13: =F13-G13 -> -8939.4218
A14: 11 | B14: Musamba Karabasis | C14: =Savings!O14 -> 41150 | D14: ='Total Interest earned'!O15 -> 11808.671 | E14: ='Penalty interest'!M14 -> 53.076923 | F14: =C14+D14+E14 -> 53011.748 | G14: ='Loan statements'!G193 -> 14600 | H14: =F14-G14 -> 38411.748
A15: 12 | B15: Osward Nkhoma | C15: =Savings!O15 -> 8200 | D15: ='Total Interest earned'!O16 -> 2420.8477 | E15: ='Penalty interest'!M15 -> 53.076923 | F15: =C15+D15+E15 -> 10673.925 | G15: ='Loan statements'!G194 -> 0 | H15: =F15-G15 -> 10673.925
A16: 13 | B16: Tiza Silavwe | C16: =Savings!O16 -> 6000 | D16: ='Total Interest earned'!O17 -> 1748.6369 | E16: ='Penalty interest'!M16 -> 53.076923 | F16: =C16+D16+E16 -> 7801.7138 | G16: ='Loan statements'!G195 -> 10750 | H16: =F16-G16 -> -2948.2862
C18: =SUM(C4:C17) -> 300350 | D18: =SUM(D4:D17) -> 82517.513 | E18: =SUM(E4:E17) -> 690 | F18: =SUM(F4:F17) -> 383557.51 | G18: =SUM(G4:G17) -> 383557.51 | H18: 0

Sheet Savings
A1: Social Shreholders Savings
C2: 45658 | D2: 45689 | E2: 45717 | F2: 45748 | G2: 45778 | H2: 45809 | I2: 45839 | J2: 45870 | K2: 45901 | L2: 45931 | M2: 45962 | N2: 45992 | O2: Total
A3: Number | B3: Members Name
A4: 1 | B4: Aibaki Tembo | C4: =1250 -> 1250 | D4: 9800 | E4: 500 | F4: =Declarations!C61 -> 500 | G4: =Declarations!C80 -> 850 | H4: =Declarations!C98 -> 500 | I4: =Declarations!C118 -> 500 | J4: 500 | K4: 500 | O4: =SUM(C4:N4) -> 14900
A5: 2 | B5: Brian Chirwa | C5: 1500 | D5: 2000 | E5: 2000 | F5: =Declarations!C62 -> 2000 | G5: =Declarations!C81 -> 3000 | H5: =Declarations!C99 -> 3000 | I5: 500 | J5: 500 | K5: 1500 | O5: =SUM(C5:N5) -> 16000
A6: 3 | B6: Chilu Nyendwa | C6: 5000 | D6: 500 | E6: 500 | F6: =Declarations!C63 -> 500 | G6: =Declarations!C82 -> 13500 | H6: =Declarations!C100 -> 500 | I6: 500 | J6: 1050 | K6: 1050 | O6: =SUM(C6:N6) -> 23100
A7: 4 | B7: Clive Makala | C7: 20000 | D7: 500 | E7: 500 | F7: =Declarations!C64 -> 500 | G7: =Declarations!C83 -> 500 | H7: =Declarations!C101 -> 3000 | I7: =Declarations!C121 -> 500 | J7: 500 | K7: 500 | O7: =SUM(C7:N7) -> 26500
A8: 5 | B8: David Machungwa | C8: 500 | D8: 31500 | E8: 500 | F8: =Declarations!C65 -> 500 | G8: =Declarations!C84 -> 500 | H8: =Declarations!C102 -> 500 | I8: =Declarations!C122 -> 500 | J8: 500 | K8: 16350 | O8: =SUM(C8:N8) -> 51350
A9: 6 | B9: Kababa Kangwa | C9: 9250 | D9: 20750 | E9: 2000 | F9: =Declarations!C66 -> 1000 | G9: =Declarations!C85 -> 2000 | H9: =Declarations!C103 -> 500 | I9: =Declarations!C123 -> 500 | J9: 500 | K9: 500 | O9: =SUM(C9:N9) -> 37000
A10: 7 | B10: Kalenga Kamwendo | C10: 500 | D10: 600 | E10: 750 | F10: =Declarations!C67 -> 550 | G10: =Declarations!C86 -> 850 | H10: =Declarations!C104 -> 500 | I10: =Declarations!C124 -> 2850 | J10: 1200 | K10: 500 | O10: =SUM(C10:N10) -> 8300
A11: 8 | B11: Kote Nikoi | C11: 11000 | D11: 500 | E11: 500 | F11: =Declarations!C68 -> 550 | G11: =Declarations!C87 -> 500 | H11: =Declarations!C105 -> 550 | I11: =Declarations!C125 -> 500 | J11: 500 | K11: 500 | O11: =SUM(C11:N11) -> 15100
A12: 9 | B12: Kunda Maliti | C12: 1000 | D12: 7000 | E12: 10000 | F12: =Declarations!C69 -> 1000 | G12: =Declarations!C88 -> 1000 | H12: =Declarations!C106 -> 2850 | I12: =Declarations!C126 -> 2350 | J12: 2000 | K12: 1200 | O12: =SUM(C12:N12) -> 28400
A13: 10 | B13: Mapenzi Mweetwa | C13: 500 | D13: 850 | E13: 20000 | F13: =Declarations!C70 -> 500 | G13: =Declarations!C89 -> 500 | H13: =Declarations!C107 -> 500 | I13: =Declarations!C127 -> 500 | J13: 500 | K13: 500 | O13: =SUM(C13:N13) -> 24350
A14: 11 | B14: Musamba Karabasis | C14: 0 | D14: 9850 | E14: 7900 | F14: =Declarations!C71 -> 4800 | G14: =Declarations!C90 -> 5100 | H14: =Declarations!C108 -> 5100 | I14: =Declarations!C128 -> 3100 | J14: 2200 | K14: 3100 | O14: =SUM(C14:N14) -> 41150
A15: 12 | B15: Osward Nkhoma | C15: 500 | D15: 1000 | E15: 1000 | F15: =Declarations!C72 -> 1000 | G15: =Declarations!C91 -> 1200 | H15: =Declarations!C109 -> 500 | I15: =Declarations!C129 -> 1000 | J15: 1000 | K15: 1000 | O15: =SUM(C15:N15) -> 8200
A16: 13 | B16: Tiza Silavwe | C16: 500 | D16: 700 | E16: 600 | F16: =Declarations!C73 -> 800 | G16: =Declarations!C92 -> 600 | H16: =Declarations!C110 -> 700 | I16: =Declarations!C130 -> 600 | J16: 700 | K16: 800 | O16: =SUM(C16:N16) -> 6000
C18: =SUM(C4:C17) -> 51500 | D18: =SUM(D4:D17) -> 85550 | E18: =SUM(E4:E16) -> 46750 | F18: =SUM(F4:F16) -> 14200 | G18: =SUM(G4:G16) -> 30100 | H18: =SUM(H4:H16) -> 18700 | I18: =SUM(I4:I16) -> 13900 | J18: =SUM(J4:J16) -> 11650 | K18: =SUM(K4:K16) -> 28000 | O18: =SUM(O4:O17) -> 300350

Sheet Declarations
A1: Declarations | B1: January
C2: Savings | D2: Loan Repayment | E2: Birthdays | F2: Admin | I2: Total
A3: Number | B3: Members Name
A4: 1 | B4: Aibaki Tembo | C4: 1250 | D4: 0 | E4: 200 | F4: 50 | I4: =SUM(C4:F4) -> 1500
A5: 2 | B5: Brian Chilu | C5: 1500 | D5: 0 | E5: 200 | F5: 50 | I5: =SUM(C5:F5) -> 1750
A6: 3 | B6: Chilu Nyendwa | C6: 5000 | D6: 0 | E6: 0 | F6: 50 | I6: =SUM(C6:F6) -> 5050
A7: 4 | B7: Clive Makala | C7: 20000 | D7: 0 | E7: 0 | F7: 50 | I7: =SUM(C7:F7) -> 20050
A8: 5 | B8: David Machungwa | C8: 500 | D8: 0 | E8: 200 | F8: 50 | I8: =SUM(C8:F8) -> 750
A9: 6 | B9: Kababa Kangwa | C9: 9250 | D9: 0 | E9: 200 | F9: 50 | I9: =SUM(C9:F9) -> 9500
A10: 7 | B10: Kalenga Kamwendo | C10: 500 | D10: 0 | E10: 200 | F10: 50 | I10: =SUM(C10:F10) -> 750
A11: 8 | B11: Kote Nikoi | C11: 11000 | D11: 0 | E11: 200 | F11: 50 | I11: =SUM(C11:F11) -> 11250
A12: 9 | B12: Kunda Maliti | C12: 1000 | D12: 0 | E12: 200 | F12: 50 | I12: =SUM(C12:F12) -> 1250
A13: 10 | B13: Mapenzi Mweetwa | C13: 500 | D13: 0 | E13: 200 | F13: 50 | I13: =SUM(C13:F13) -> 750
A14: 11 | B14: Musamba Karabasis | C14: 0 | D14: 0 | E14: 200 | F14: 50 | I14: =SUM(C14:F14) -> 250
A15: 12 | B15: Osward Nkhoma | C15: 500 | D15: 0 | E15: 200 | F15: 50 | I15: =SUM(C15:F15) -> 750
A16: 13 | B16: Tiza Silavwe | C16: 500 | D16: 0 | E16: 200 | F16: 50 | I16: =SUM(C16:F16) -> 750
C18: =SUM(C4:C17) -> 51500 | D18: =SUM(D4:D17) -> 0 | E18: =SUM(E4:E17) -> 2200 | F18: =SUM(F4:F17) -> 650 | I18: =SUM(I4:I17) -> 54350
A20: Declarations | B20: February
C21: Savings | D21: Jan Loan Repayment | E21: Birthdays | F21: Admin | I21: Total
A22: Number | B22: Members Name
A23: 1 | B23: Aibaki Tembo | C23: 9800 | D23: 0 | E23: 0 | F23: 50 | I23: =SUM(C23:F23) -> 9850
A24: 2 | B24: Brian Chilu | C24: 2000 | D24: 0 | E24: 100 | F24: 50 | I24: =SUM(C24:F24) -> 2150
A25: 3 | B25: Chilu Nyendwa | C25: 500 | D25: 1600 | E25: 100 | F25: 50 | I25: =SUM(C25:F25) -> 2250
A26: 4 | B26: Clive Makala | C26: 500 | D26: 4000 | E26: 100 | F26: 50 | I26: =SUM(C26:F26) -> 4650
A27: 5 | B27: David Machungwa | C27: 31500 | D27: 0 | E27: 100 | F27: 50 | I27: =SUM(C27:F27) -> 31650
A28: 6 | B28: Kababa Kangwa | C28: 20750 | D28: 0 | E28: 100 | F28: 50 | I28: =SUM(C28:F28) -> 20900
A29: 7 | B29: Kalenga Kamwendo | C29: 600 | D29: 0 | E29: 100 | F29: 50 | I29: =SUM(C29:F29) -> 750
A30: 8 | B30: Kote Nikoi | C30: 500 | D30: 0 | E30: 100 | F30: 50 | I30: =SUM(C30:F30) -> 650
A31: 9 | B31: Kunda Maliti | C31: 7000 | D31: 0 | E31: 100 | F31: 50 | I31: =SUM(C31:F31) -> 7150
A32: 10 | B32: Mapenzi Mweetwa | C32: 850 | D32: 0 | E32: 100 | F32: 50 | I32: =SUM(C32:F32) -> 1000
A33: 11 | B33: Musamba Karabasis | C33: 9850 | D33: 0 | E33: 100 | F33: 50 | I33: =SUM(C33:F33) -> 10000
A34: 12 | B34: Osward Nkhoma | C34: 1000 | D34: 0 | E34: 100 | F34: 50 | I34: =SUM(C34:F34) -> 1150
A35: 13 | B35: Tiza Silavwe | C35: 700 | D35: 650 | E35: 100 | F35: 50 | I35: =SUM(C35:F35) -> 1500
C37: =SUM(C23:C36) -> 85550 | D37: =SUM(D23:D36) -> 6250 | E37: =SUM(E23:E36) -> 1200 | F37: =SUM(F23:F36) -> 650 | I37: =SUM(I23:I36) -> 93650
A39: Declarations | B39: March
C40: Savings | D40: Jan Loan Repayment | E40: Feb Loan Repayment | F40: Birthdays | I40: Admin | J40: Total
A41: Number | B41: Members Name
A42: 1 | B42: Aibaki Tembo | C42: 500 | D42: 0 | F42: 200 | I42: 50 | J42: =SUM(C42:I42) -> 750
A43: 2 | B43: Brian Chirwa | C43: 2000 | D43: 0 | F43: 200 | I43: 50 | J43: =SUM(C43:I43) -> 2250
A44: 3 | B44: Chilu Nyendwa | C44: 500 | D44: 1150 | F44: 200 | I44: 50 | J44: =SUM(C44:I44) -> 1900
A45: 4 | B45: Clive Makala | C45: 500 | D45: 4000 | F45: 200 | I45: 50 | J45: =SUM(C45:I45) -> 4750
A46: 5 | B46: David Machungwa | C46: 500 | D46: 0 | E46: 3500 | F46: 200 | I46: 50 | J46: =SUM(C46:I46) -> 4250
A47: 6 | B47: Kababa Kangwa | C47: 2000 | D47: 0 | E47: 2070 | F47: 200 | I47: 50 | J47: =SUM(C47:I47) -> 4320
A48: 7 | B48: Kalenga Kamwendo | C48: 750 | D48: 0 | F48: 200 | I48: 50 | J48: =SUM(C48:I48) -> 1000
A49: 8 | B49: Kote Nikoi | C49: 500 | D49: 0 | E49: 2000 | F49: 200 | I49: 50 | J49: =SUM(C49:I49) -> 2750
A50: 9 | B50: Kunda Maliti | C50: 10000 | D50: 0 | F50: 200 | I50: 50 | J50: =SUM(C50:I50) -> 10250
A51: 10 | B51: Mapenzi Mweetwa | C51: 20000 | D51: 0 | F51: 100 | I51: 50 | J51: =SUM(C51:I51) -> 20150
A52: 11 | B52: Musamba Karabasis | C52: 7900 | D52: 0 | F52: 200 | I52: 50 | J52: =SUM(C52:I52) -> 8150
A53: 12 | B53: Osward Nkhoma | C53: 1000 | D53: 0 | F53: 200 | I53: 50 | J53: =SUM(C53:I53) -> 1250
A54: 13 | B54: Tiza Silavwe | C54: 600 | D54: 1075 | F54: 100 | I54: 50 | J54: =SUM(C54:I54) -> 1825
C56: =SUM(C42:C55) -> 46750 | D56: =SUM(D42:D55) -> 6225 | E56: =SUM(E42:E55) -> 7570 | F56: =SUM(F42:F55) -> 2400 | I56: =SUM(I42:I55) -> 650 | J56: =SUM(J42:J55) -> 63595
A58: Declarations | B58: April
C59: Savings | D59: Jan Loan Repayment | E59: Feb Loan Repayment | F59: Mar Loan Repayment | H59: Penalty | I59: Birthdays | J59: Admin | K59: Total
A60: Number | B60: Members Name
A61: 1 | B61: Aibaki Tembo | C61: 500 | D61: 0 | E61: 0 | F61: 0 | H61: 0 | I61: 100 | J61: 50 | K61: =SUM(C61:J61) -> 650 | L61: paid
A62: 2 | B62: Brian Chirwa | C62: 2000 | D62: 0 | E62: 0 | F62: 0 | H62: 0 | I62: 100 | J62: 50 | K62: =SUM(C62:J62) -> 2150 | L62: paid
A63: 3 | B63: Chilu Nyendwa | C63: 500 | D63: 1150 | E63: 0 | F63: 0 | H63: 0 | I63: 100 | J63: 50 | K63: =SUM(C63:J63) -> 1800 | L63: paid
A64: 4 | B64: Clive Makala | C64: 500 | D64: 5500 | E64: 0 | F64: 1000 | H64: 0 | I64: 100 | J64: 50 | K64: =SUM(C64:J64) -> 7150 | L64: paid
A65: 5 | B65: David Machungwa | C65: 500 | D65: 0 | E65: 3500 | F65: 0 | H65: 0 | I65: 0 | J65: 50 | K65: =SUM(C65:J65) -> 4050 | L65: paid
A66: 6 | B66: Kababa Kangwa | C66: 1000 | D66: 0 | E66: 0 | F66: 0 | H66: 0 | I66: 100 | J66: 50 | K66: =SUM(C66:J66) -> 1150 | L66: paid
A67: 7 | B67: Kalenga Kamwendo | C67: 550 | H67: 300 | I67: 100 | J67: 50 | K67: =SUM(C67:J67) -> 1000 | L67: paid
A68: 8 | B68: Kote Nikoi | C68: 550 | D68: 0 | E68: 2300 | F68: 0 | H68: 0 | I68: 100 | J68: 50 | K68: =SUM(C68:J68) -> 3000 | L68: paid
A69: 9 | B69: Kunda Maliti | C69: 1000 | F69: 2750 | H69: 0 | I69: 100 | J69: 50 | K69: =SUM(C69:J69) -> 3900 | L69: paid
A70: 10 | B70: Mapenzi Mweetwa | C70: 500 | H70: 0 | I70: 100 | J70: 50 | K70: =SUM(C70:J70) -> 650 | L70: paid
A71: 11 | B71: Musamba Karabasis | C71: 4800 | H71: 300 | I71: 100 | J71: 50 | K71: =SUM(C71:J71) -> 5250 | L71: paid
A72: 12 | B72: Osward Nkhoma | C72: 1000 | D72: 0 | E72: 0 | F72: 0 | H72: 0 | I72: 100 | J72: 50 | K72: =SUM(C72:J72) -> 1150 | L72: paid
A73: 13 | B73: Tiza Silavwe | C73: 800 | D73: 0 | E73: 0 | F73: 0 | H73: 0 | I73: 100 | J73: 50 | K73: =SUM(C73:J73) -> 950 | L73: paid
C75: =SUM(C61:C74) -> 14200 | D75: =SUM(D61:D74) -> 6650 | E75: =SUM(E61:E74) -> 5800 | F75: =SUM(F61:F74) -> 3750 | H75: =SUM(H61:H74) -> 600 | I75: =SUM(I61:I74) -> 1200 | J75: =SUM(J61:J74) -> 650 | K75: =SUM(K61:K74) -> 32850
A77: Declarations | B77: May
C78: Savings | D78: Jan Loan Repayment | E78: Feb Loan Repayment | F78: Mar Loan Repayment | G78: Apr Loan Repayment | H78: Penalty | I78: Birthdays | J78: Admin | K78: Total
A79: Number | B79: Members Name
A80: 1 | B80: Aibaki Tembo | C80: 850 | I80: 100 | J80: 50 | K80: =SUM(C80:J80) -> 1000
A81: 2 | B81: Brian Chirwa | C81: 3000 | G81: 2000 | I81: 100 | J81: 50 | K81: =SUM(C81:J81) -> 5150
A82: 3 | B82: Chilu Nyendwa | C82: =500+13000 -> 13500 | D82: 7600 | G82: 0 | I82: 100 | J82: 50 | K82: =SUM(C82:J82) -> 21250
A83: 4 | B83: Clive Makala | C83: 500 | D83: 4600 | G83: 0 | I83: 100 | J83: 50 | K83: =SUM(C83:J83) -> 5250
A84: 5 | B84: David Machungwa | C84: 500 | E84: 3500 | G84: 0 | I84: 100 | J84: 50 | K84: =SUM(C84:J84) -> 4150
A85: 6 | B85: Kababa Kangwa | C85: 2000 | I85: 100 | J85: 50 | K85: =SUM(C85:J85) -> 2150
A86: 7 | B86: Kalenga Kamwendo | C86: 850 | I86: 100 | J86: 50 | K86: =SUM(C86:J86) -> 1000
A87: 8 | B87: Kote Nikoi | C87: 500 | E87: 2300 | G87: 0 | I87: 100 | J87: 50 | K87: =SUM(C87:J87) -> 2950
A88: 9 | B88: Kunda Maliti | C88: 1000 | F88: 2850 | G88: 0 | I88: 100 | J88: 50 | K88: =SUM(C88:J88) -> 4000
A89: 10 | B89: Mapenzi Mweetwa | C89: 500 | G89: 5000 | I89: 100 | J89: 50 | K89: =SUM(C89:J89) -> 5650
A90: 11 | B90: Musamba Karabasis | C90: 5100 | I90: 100 | J90: 50 | K90: =SUM(C90:J90) -> 5250
A91: 12 | B91: Osward Nkhoma | C91: 1200 | G91: 1150 | I91: 0 | J91: 50 | K91: =SUM(C91:J91) -> 2400
A92: 13 | B92: Tiza Silavwe | C92: 600 | I92: 100 | J92: 50 | K92: =SUM(C92:J92) -> 750
C94: =SUM(C80:C93) -> 30100 | D94: =SUM(D80:D93) -> 12200 | E94: =SUM(E80:E93) -> 5800 | F94: =SUM(F80:F93) -> 2850 | G94: =SUM(G80:G93) -> 8150 | H94: =SUM(H80:H93) -> 0 | I94: =SUM(I80:I93) -> 1200 | J94: =SUM(J80:J93) -> 650 | K94: =SUM(K80:K93) -> 60950
A95: Declarations | B95: June
C96: Savings | D96: Jan Loan Repayment | E96: Feb Loan Repayment | F96: Mar Loan Repayment | G96: Apr Loan Repayment | H96: May Loan Repayment | I96: Penalty | J96: Birthdays | K96: Admin | L96: Total
A97: Number | B97: Members Name
A98: 1 | B98: Aibaki Tembo | C98: 500 | J98: 100 | K98: 50 | L98: =SUM(C98:K98) -> 650
A99: 2 | B99: Brian Chirwa | C99: 3000 | G99: 2950 | J99: 0 | K99: 50 | L99: =SUM(C99:K99) -> 6000
A100: 3 | B100: Chilu Nyendwa | C100: 500 | D100: 0 | H100: 4600 | J100: 100 | K100: 50 | L100: =SUM(C100:K100) -> 5250
A101: 4 | B101: Clive Makala | C101: 3000 | D101: 27900 | F101: 5376.75 | J101: 100 | K101: 50 | L101: =SUM(C101:K101) -> 36426.75
A102: 5 | B102: David Machungwa | C102: 500 | E102: 3500 | J102: 100 | K102: 50 | L102: =SUM(C102:K102) -> 4150
A103: 6 | B103: Kababa Kangwa | C103: 500 | H103: 2100 | J103: 100 | K103: 50 | L103: =SUM(C103:K103) -> 2750
A104: 7 | B104: Kalenga Kamwendo | C104: 500 | J104: 100 | K104: 50 | L104: =SUM(C104:K104) -> 650
A105: 8 | B105: Kote Nikoi | C105: 550 | E105: 2300 | G105: 0 | J105: 100 | K105: 50 | L105: =SUM(C105:K105) -> 3000
A106: 9 | B106: Kunda Maliti | C106: 2850 | F106: 5000 | G106: 0 | J106: 100 | K106: 50 | L106: =SUM(C106:K106) -> 8000
A107: 10 | B107: Mapenzi Mweetwa | C107: 500 | G107: 5350 | J107: 100 | K107: 50 | L107: =SUM(C107:K107) -> 6000
A108: 11 | B108: Musamba Karabasis | C108: 5100 | J108: 100 | K108: 50 | L108: =SUM(C108:K108) -> 5250
A109: 12 | B109: Osward Nkhoma | C109: 500 | G109: 1150 | J109: 100 | K109: 50 | L109: =SUM(C109:K109) -> 1800
...

Sheet Loan statements
A1: Social Shreholders Loan | C1: 45658
C2: Loans | D2: Int on loans | E2: Total Loan | F2: Repayment | G2: Loan | H2: Note | I2: Min payment
A3: Number | B3: Members Name
A4: 1 | B4: Aibaki Tembo | G4: =E4-F4 -> 0
A5: 2 | B5: Brian Chirwa | G5: =E5-F5 -> 0
A6: 3 | B6: Chilu Nyendwa | C6: 10000 | D6: =C6*0.15 -> 1500 | E6: =C6+D6 -> 11500 | F6: 1600 | G6: =E6-F6 -> 9900 | H6: 05.05.2025 | I6: =E6*0.1 -> 1150
A7: 4 | B7: Clive Makala | C7: 40000 | D7: =C7*0.15 -> 6000 | E7: =C7+D7 -> 46000 | F7: 4000 | G7: =E7-F7 -> 42000 | H7: 05.06.2025 | I7: =E7*0.1 -> 4600
B8: David Machungwa | F8: 0 | G8: =E8-F8 -> 0
A9: 6 | B9: Kababa Kangwa | F9: 0 | G9: =E9-F9 -> 0
A10: 7 | B10: Kalenga Kamwendo | F10: 0 | G10: =E10-F10 -> 0
A11: 8 | B11: Kote Nikoi | F11: 0 | G11: =E11-F11 -> 0
A12: 9 | B12: Kunda Maliti | F12: 0 | G12: =E12-F12 -> 0
A13: 10 | B13: Mapenzi Mweetwa | F13: 0 | G13: =E13-F13 -> 0
A14: 11 | B14: Musamba Karabasis | F14: 0 | G14: =E14-F14 -> 0
A15: 12 | B15: Osward Nkhoma | F15: 0 | G15: =E15-F15 -> 0
A16: 13 | B16: Tiza Silavwe | C16: 1500 | D16: =C16*0.15 -> 225 | E16: =C16+D16 -> 1725 | F16: 650 | G16: =E16-F16 -> 1075 | H16: 05.02.2025 | I16: =E16/2 -> 862.5
C18: =SUM(C4:C17) -> 51500 | D18: =SUM(D4:D17) -> 7725 | E18: =SUM(E4:E17) -> 59225 | F18: =SUM(F4:F17) -> 6250 | G18: =SUM(G4:G17) -> 52975
A21: Social Shreholders | C21: 45689
A22: Outstanding Loans | C22: Loans | D22: Int on loans | E22: Total Loan | F22: Repayment | G22: Loan | H22: Note | I22: Min payment
A23: Number | B23: Members Name
A24: 1 | B24: Aibaki Tembo | C24: 0 | F24: 0 | G24: =C24+D24-F24 -> 0
A25: 2 | B25: Brian Chirwa | C25: 0 | F25: 0 | G25: =C25+D25-F25 -> 0
A26: 3 | B26: Chilu Nyendwa | C26: 9900 | D26: 0 | E26: =C26+D26 -> 9900 | F26: 1150 | G26: =C26+D26-F26 -> 8750 | H26: 05.05.2025 | I26: 1150
A27: 4 | B27: Clive Makala | C27: 42000 | D27: 0 | E27: =C27+D27 -> 42000 | F27: 4000 | G27: =C27+D27-F27 -> 38000 | H27: 05.06.2025 | I27: 4600
B28: David Machungwa | C28: 70000 | D28: =C28*0.15 -> 10500 | E28: =C28+D28 -> 80500 | F28: 3500 | G28: =C28+D28-F28 -> 77000 | H28: 05.07.2025 | I28: =E28*0.1 -> 8050
A29: 6 | B29: Kababa Kangwa | C29: 1800 | D29: =C29*0.15 -> 270 | E29: =C29+D29 -> 2070 | F29: 2070 | G29: =C29+D29-F29 -> 0 | H29: 05.03.2025 | I29: 2070
A30: 7 | B30: Kalenga Kamwendo | C30: 0 | D30: =C30*0.15 -> 0 | E30: =C30+D30 -> 0 | F30: 0 | G30: =C30+D30-F30 -> 0
A31: 8 | B31: Kote Nikoi | C31: 20000 | D31: =C31*0.15 -> 3000 | E31: =C31+D31 -> 23000 | F31: 2000 | G31: =C31+D31-F31 -> 21000 | H31: 05.07.2025 | I31: =E31*0.1 -> 2300
A32: 9 | B32: Kunda Maliti | C32: 0 | E32: =C32+D32 -> 0 | F32: 0 | G32: =C32+D32-F32 -> 0
A33: 10 | B33: Mapenzi Mweetwa | C33: 0 | E33: =C33+D33 -> 0 | F33: 0 | G33: =C33+D33-F33 -> 0
A34: 11 | B34: Musamba Karabasis | C34: 0 | E34: =C34+D34 -> 0 | F34: 0 | G34: =C34+D34-F34 -> 0
A35: 12 | B35: Osward Nkhoma | C35: 0 | E35: =C35+D35 -> 0 | F35: 0 | G35: =C35+D35-F35 -> 0
A36: 13 | B36: Tiza Silavwe | C36: 1075 | D36: 0 | E36: =C36+D36 -> 1075 | F36: 1075 | G36: =C36+D36-F36 -> 0 | H36: 05.03.2025 | I36: 1075
C38: =SUM(C24:C37) -> 144775 | D38: =SUM(D24:D37) -> 13770 | E38: =SUM(E24:E37) -> 158545 | F38: =SUM(F24:F37) -> 13795 | G38: =SUM(G24:G37) -> 144750
A41: Social Shreholders Loan | C41: 45717
C42: Loans | D42: Int on loans | E42: Total Loan | F42: Repayment | G42: Loan | H42: Note | I42: Min payment
A43: Number | B43: Members Name
A44: 1 | B44: Aibaki Tembo | C44: 0 | D44: 0 | F44: 0 | G44: =C44+D44-F44 -> 0
A45: 2 | B45: Brian Chirwa | C45: 0 | D45: 0 | F45: 0 | G45: =C45+D45-F45 -> 0
A46: 3 | B46: Chilu Nyendwa | C46: =G26 -> 8750 | D46: 0 | E46: =C46+D46 -> 8750 | F46: =Declarations!D63 -> 1150 | G46: =C46+D46-F46 -> 7600 | H46: 05.05.2025 | I46: 1150
A47: 4 | B47: Clive Makala | C47: =G27 -> 38000 | D47: 0 | E47: =C47+D47 -> 38000 | F47: =Declarations!D64 -> 5500 | G47: =C47+D47-F47 -> 32500 | H47: 05.06.2025 | I47: 4600
A48: 4 | B48: Clive Makala - Loan 2 | C48: 5545 | D48: =C48*0.15 -> 831.75 | E48: =C48+D48 -> 6376.75 | F48: =Declarations!F64 -> 1000 | G48: =C48+D48-F48 -> 5376.75 | H48: 05.05.2025 | I48: =E48*0.1 -> 637.675
A49: 5 | B49: David Machungwa | C49: =G28 -> 77000 | D49: 0 | E49: =C49+D49 -> 77000 | F49: =Declarations!E65 -> 3500 | G49: =C49+D49-F49 -> 73500 | H49: 05.07.2025 | I49: 8050
A50: 6 | B50: Kababa Kangwa | C50: =G29 -> 0 | D50: 0 | E50: =C50+D50 -> 0 | F50: 0 | G50: =C50+D50-F50 -> 0
A51: 7 | B51: Kalenga Kamwendo | C51: =G30 -> 0 | D51: 0 | E51: =C51+D51 -> 0 | F51: 0 | G51: =C51+D51-F51 -> 0
A52: 8 | B52: Kote Nikoi | C52: =G31 -> 21000 | D52: 0 | E52: =C52+D52 -> 21000 | F52: =Declarations!E68 -> 2300 | G52: =C52+D52-F52 -> 18700 | H52: 05.07.2025 | I52: 2300
A53: 9 | B53: Kunda Maliti | C53: 55000 | D53: =C53*0.15 -> 8250 | E53: =C53+D53 -> 63250 | F53: =Declarations!F69 -> 2750 | G53: =C53+D53-F53 -> 60500 | H53: 05.08.2025 | I53: =G53/10 -> 6050
A54: 10 | B54: Mapenzi Mweetwa | C54: =G33 -> 0 | E54: =C54+D54 -> 0 | F54: 0 | G54: =C54+D54-F54 -> 0
A55: 11 | B55: Musamba Karabasis | C55: =G34 -> 0 | E55: =C55+D55 -> 0 | F55: 0 | G55: =C55+D55-F55 -> 0
A56: 12 | B56: Osward Nkhoma | C56: =G35 -> 0 | E56: =C56+D56 -> 0 | F56: 0 | G56: =C56+D56-F56 -> 0
A57: 13 | B57: Tiza Silavwe | C57: =G36 -> 0 | D57: 0 | E57: =C57+D57 -> 0 | F57: 0 | G57: =C57+D57-F57 -> 0
C59: =SUM(C44:C58) -> 205295 | D59: =SUM(D44:D58) -> 9081.75 | E59: =SUM(E44:E58) -> 214376.75 | F59: =SUM(F44:F58) -> 16200 | G59: =SUM(G44:G58) -> 198176.75
A62: Social Shreholders Loan | C62: 45748
C63: Loans | D63: Int on loans | E63: Total Loan | F63: Repayment | G63: Loan | H63: Note | I63: Min payment
A64: Number | B64: Members Name
A65: 1 | B65: Aibaki Tembo | C65: =G44 -> 0 | D65: 0 | E65: =C65+D65 -> 0 | F65: 0 | G65: =C65+D65-F65 -> 0
A66: 2 | B66: Brian Chirwa | C66: 8000 | D66: =C66*0.15 -> 1200 | E66: =C66+D66 -> 9200 | F66: =Declarations!G81 -> 2000 | G66: =C66+D66-F66 -> 7200 | H66: 05.08.2025 | I66: 920
A67: 3 | B67: Chilu Nyendwa | C67: =G46 -> 7600 | D67: 0 | E67: =C67+D67 -> 7600 | F67: =Declarations!D82 -> 7600 | G67: =C67+D67-F67 -> 0 | H67: 05.05.2025 | I67: 7600
A68: 4 | B68: Clive Makala | C68: =G47 -> 32500 | D68: 0 | E68: =C68+D68 -> 32500 | F68: =Declarations!D83 -> 4600 | G68: =C68+D68-F68 -> 27900 | H68: 05.06.2025 | I68: 4600
A69: 4 | B69: Clive Makala - Loan 2 | C69: =G48 -> 5376.75 | D69: 0 | E69: =C69+D69 -> 5376.75 | F69: 0 | G69: =C69+D69-F69 -> 5376.75 | H69: 05.06.2025 | I69: =E69*0.1 -> 537.675
A70: 5 | B70: David Machungwa | C70: =G49 -> 73500 | D70: 0 | E70: =C70+D70 -> 73500 | F70: =Declarations!E84 -> 3500 | G70: =C70+D70-F70 -> 70000 | H70: 05.07.2025 | I70: 8050
A71: 6 | B71: Kababa Kangwa | C71: =G50 -> 0 | D71: 0 | E71: =C71+D71 -> 0 | F71: 0 | G71: =C71+D71-F71 -> 0
A72: 7 | B72: Kalenga Kamwendo | C72: =G51 -> 0 | D72: 0 | E72: =C72+D72 -> 0 | F72: 0 | G72: =C72+D72-F72 -> 0
A73: 8 | B73: Kote Nikoi | C73: =G52 -> 18700 | D73: 0 | E73: =C73+D73 -> 18700 | F73: =Declarations!E87 -> 2300 | G73: =C73+D73-F73 -> 16400 | H73: 05.07.2025 | I73: 2300
A74: 9 | B74: Kunda Maliti | C74: =G53 -> 60500 | D74: 0 | E74: =C74+D74 -> 60500 | F74: =Declarations!F88 -> 2850 | G74: =C74+D74-F74 -> 57650 | H74: 05.08.2025 | I74: =G74/10 -> 5765
A75: 10 | B75: Mapenzi Mweetwa | C75: 20000 | D75: =C75*0.15 -> 3000 | E75: =C75+D75 -> 23000 | F75: =Declarations!G89 -> 5000 | G75: =C75+D75-F75 -> 18000 | H75: 05.09.2025 | I75: 2300
A76: 11 | B76: Musamba Karabasis | C76: =G55 -> 0 | D76: 0 | E76: =C76+D76 -> 0 | F76: 0 | G76: =C76+D76-F76 -> 0
A77: 12 | B77: Osward Nkhoma | C77: 3000 | D77: =C77*0.15 -> 450 | E77: =C77+D77 -> 3450 | F77: =Declarations!G91 -> 1150 | G77: =C77+D77-F77 -> 2300 | H77: 05.06.2025 | I77: 345
A78: 13 | B78: Tiza Silavwe | C78: =G57 -> 0 | D78: 0 | E78: =C78+D78 -> 0 | F78: 0 | G78: =C78+D78-F78 -> 0
C80: =SUM(C65:C79) -> 229176.75 | D80: =SUM(D65:D79) -> 4650 | E80: =SUM(E65:E79) -> 233826.75 | F80: =SUM(F65:F79) -> 29000 | G80: =SUM(G65:G79) -> 204826.75
A83: Social Shreholders Loan | C83: 45778
C84: Loans | D84: Int on loans | E84: Total Loan | F84: Repayment | G84: Loan | H84: Note | I84: Min payment
A85: Number | B85: Members Name
A86: 1 | B86: Aibaki Tembo | C86: =G65 -> 0 | D86: 0 | E86: =C86+D86 -> 0 | F86: 0 | G86: =C86+D86-F86 -> 0
A87: 2 | B87: Brian Chirwa | C87: =G66 -> 7200 | D87: 0 | E87: =C87+D87 -> 7200 | F87: =Declarations!G99 -> 2950 | G87: =C87+D87-F87 -> 4250 | H87: 05.08.2025 | I87: 920
A88: 3 | B88: Chilu Nyendwa | C88: 40000 | D88: =C88*0.15 -> 6000 | E88: =C88+D88 -> 46000 | F88: =Declarations!H100 -> 4600 | G88: =C88+D88-F88 -> 41400 | H88: 05.10.2025 | I88: 4600
A89: 4 | B89: Clive Makala | C89: =G68 -> 27900 | D89: 0 | E89: =C89+D89 -> 27900 | F89: =Declarations!D101 -> 27900 | G89: =C89+D89-F89 -> 0 | H89: 05.06.2025 | I89: 27900
A90: 4 | B90: Clive Makala - Loan 2 | C90: =G69 -> 5376.75 | D90: 0 | E90: =C90+D90 -> 5376.75 | F90: =Declarations!F101 -> 5376.75 | G90: =C90+D90-F90 -> 0 | H90: 05.06.2025 | I90: 5376.75
A91: 5 | B91: David Machungwa | C91: =G70 -> 70000 | D91: 0 | E91: =C91+D91 -> 70000 | F91: =Declarations!E102 -> 3500 | G91: =C91+D91-F91 -> 66500 | H91: 05.07.2025 | I91: 8050
A92: 6 | B92: Kababa Kangwa | C92: 19100 | D92: =C92*0.15 -> 2865 | E92: =C92+D92 -> 21965 | F92: =Declarations!H103 -> 2100 | G92: =C92+D92-F92 -> 19865 | H92: 05.10.2025 | I92: 2098
A93: 7 | B93: Kalenga Kamwendo | C93: =G72 -> 0 | D93: 0 | E93: =C93+D93 -> 0 | F93: 0 | G93: =C93+D93-F93 -> 0
A94: 8 | B94: Kote Nikoi | C94: =G73 -> 16400 | D94: 0 | E94: =C94+D94 -> 16400 | F94: =Declarations!E105 -> 2300 | G94: =C94+D94-F94 -> 14100 | H94: 05.07.2025 | I94: 2300
A95: 9 | B95: Kunda Maliti | C95: =G74 -> 57650 | D95: 0 | E95: =C95+D95 -> 57650 | F95: =Declarations!F106 -> 5000 | G95: =C95+D95-F95 -> 52650 | H95: 05.08.2025 | I95: 3025
A96: 10 | B96: Mapenzi Mweetwa | C96: =G75 -> 18000 | D96: 0 | E96: =C96+D96 -> 18000 | F96: =Declarations!G107 -> 5350 | G96: =C96+D96-F96 -> 12650 | H96: 05.09.2025 | I96: 2300
A97: 11 | B97: Musamba Karabasis | C97: =G76 -> 0 | D97: 0 | E97: =C97+D97 -> 0 | F97: =0 -> 0 | G97: =C97+D97-F97 -> 0
A98: 12 | B98: Osward Nkhoma | C98: =G77 -> 2300 | D98: 0 | E98: =C98+D98 -> 2300 | F98: =Declarations!G109 -> 1150 | G98: =C98+D98-F98 -> 1150 | H98: 05.07.2025 | I98: 2300
A99: 13 | B99: Tiza Silavwe | C99: =G78 -> 0 | D99: 0 | E99: =C99+D99 -> 0 | F99: 0 | G99: =C99+D99-F99 -> 0
C101: =SUM(C86:C100) -> 263926.75 | D101: =SUM(D86:D100) -> 8865 | E101: =SUM(E86:E100) -> 272791.75 | F101: =SUM(F86:F100) -> 60226.75 | G101: =SUM(G86:G100) -> 212565
A105: Social Shreholders Loan | C105: 45809
C106: Loans | D106: Int on loans | E106: Total Loan | F106: Repayment | G106: Loan | H106: Note | I106: Min payment
A107: Number | B107: Members Name
A108: 1 | B108: Aibaki Tembo | C108: =G86 -> 0 | D108: 0 | E108: =C108+D108 -> 0 | F108: 0 | G108: =C108+D108-F108 -> 0
A109: 2 | B109: Brian Chirwa | C109: =G87 -> 4250 | D109: 0 | E109: =C109+D109 -> 4250 | F109: =Declarations!G119 -> 4250 | G109: =C109+D109-F109 -> 0 | H109: 05.08.2025 | I109: 920
A110: 3 | B110: Chilu Nyendwa | C110: =G88 -> 41400 | D110: 0 | E110: =C110+D110 -> 41400 | F110: =Declarations!H120 -> 4600 | G110: =C110+D110-F110 -> 36800 | H110: 05.10.2025 | I110: 4600
A111: 4 | B111: Clive Makala | C111: ='Loans disbursed'!H7 -> 68926.75 | D111: =C111*0.15 -> 10339.012 | E111: =C111+D111 -> 79265.762 | F111: =Declarations!H121 -> 4500 | G111: =C111+D111-F111 -> 74765.762 | H111: 05.11.2025 | I111: 3900
A112: 5 | B112: David Machungwa | C112: =G91 -> 66500 | D112: 0 | E112: =C112+D112 -> 66500 | F112: =Declarations!E122 -> 3500 | G112: =C112+D112-F112 -> 63000 | H112: 05.07.2025 | I112: 3500
A113: 6 | B113: Kababa Kangwa | C113: =G92 -> 19865 | D113: 0 | E113: =C113+D113 -> 19865 | F113: =Declarations!H123 -> 2100 | G113: =C113+D113-F113 -> 17765 | H113: 05.10.2025 | I113: 2098
A114: 7 | B114: Kalenga Kamwendo | C114: =G93 -> 0 | D114: =C114*0.15 -> 0 | E114: =C114+D114 -> 0 | F114: 0 | G114: =C114+D114-F114 -> 0
A115: 8 | B115: Kote Nikoi | C115: =G94 -> 14100 | D115: 0 | E115: =C115+D115 -> 14100 | F115: =Declarations!E125 -> 14100 | G115: =C115+D115-F115 -> 0 | H115: 05.07.2025 | I115: 14100
A116: 8 | B116: Kote Nikoi - 2 | C116: ='Loans disbursed'!H11 -> 10000 | D116: =C116*0.15 -> 1500 | E116: =C116+D116 -> 11500 | F116: =Declarations!I125 -> 1150 | G116: =C116+D116-F116 -> 10350 | H116: 05.10.2025 | I116: 1150
...

Sheet Loans disbursed
A1: Social Shreholders Loan Disbursements
C2: 45658 | D2: 45689 | E2: 45717 | F2: 45748 | G2: 45778 | H2: 45809 | I2: 45839 | J2: 45870 | K2: 45901 | L2: 45931 | M2: 45962 | N2: 45992 | O2: TOTAL LOANS
A3: Number | B3: Members Name
A4: 1 | B4: Aibaki Tembo | C4: 0 | D4: 0 | E4: 0 | F4: 0 | G4: 0 | H4: 0 | I4: 0 | J4: 0 | K4: 9420 | O4: =SUM(C4:K4) -> 9420
A5: 2 | B5: Brian Chilu | C5: 0 | D5: 0 | E5: 0 | F5: 8000 | G5: 0 | H5: 0 | I5: 7000 | J5: 0 | K5: 5000 | O5: =SUM(C5:K5) -> 20000
A6: 3 | B6: Chilu Nyendwa | C6: 10000 | D6: 0 | E6: 0 | F6: 0 | G6: 40000 | H6: 0 | I6: 0 | J6: 22325 | K6: 0 | O6: =SUM(C6:K6) -> 72325
A7: 4 | B7: Clive Makala | C7: 40000 | D7: 0 | E7: 5545 | F7: 0 | G7: 0 | H7: 68926.75 | I7: 5100 | J7: 0 | K7: 0 | O7: =SUM(C7:K7) -> 119571.75
A8: 5 | B8: David Machungwa | D8: 70000 | E8: 0 | F8: 0 | G8: 0 | H8: 0 | I8: 0 | J8: 0 | K8: 0 | O8: =SUM(C8:K8) -> 70000
A9: 6 | B9: Kababa Kangwa | D9: 1800 | E9: 0 | F9: 0 | G9: 19100 | H9: 0 | I9: 0 | J9: 0 | K9: 0 | O9: =SUM(C9:K9) -> 20900
A10: 7 | B10: Kalenga Kamwendo | D10: 0 | E10: 0 | F10: 0 | G10: 0 | H10: 0 | I10: 0 | J10: 0 | K10: 50000 | O10: =SUM(C10:K10) -> 50000
A11: 8 | B11: Kote Nikoi | D11: 20000 | E11: 0 | F11: 0 | G11: 0 | H11: 10000 | I11: 6000 | J11: 0 | K11: 0 | O11: =SUM(C11:K11) -> 36000
A12: 9 | B12: Kunda Maliti | D12: 0 | E12: 55000 | F12: 0 | G12: 0 | H12: 0 | I12: 0 | J12: 0 | K12: 0 | O12: =SUM(C12:K12) -> 55000
A13: 10 | B13: Mapenzi Mweetwa | D13: 0 | E13: 0 | F13: 20000 | G13: 0 | H13: 0 | I13: 6000 | J13: 30000 | K13: 0 | O13: =SUM(C13:K13) -> 56000
A14: 11 | B14: Musamba Karabasis | D14: 0 | E14: 0 | F14: 0 | G14: 0 | H14: 0 | I14: 25000 | J14: 0 | K14: 0 | O14: =SUM(C14:K14) -> 25000
A15: 12 | B15: Osward Nkhoma | D15: 0 | E15: 0 | F15: 3000 | G15: 0 | H15: 0 | I15: 0 | J15: 0 | K15: 0 | O15: =SUM(C15:K15) -> 3000
A16: 13 | B16: Tiza Silavwe | C16: 1500 | D16: 0 | E16: 0 | F16: 0 | G16: 0 | H16: 0 | I16: 12000 | J16: 0 | K16: 0 | O16: =SUM(C16:K16) -> 13500
C18: =SUM(C4:C17) -> 51500 | D18: =SUM(D4:D17) -> 91800 | E18: =SUM(E4:E17) -> 60545 | F18: =SUM(F4:F17) -> 31000 | G18: =SUM(G4:G17) -> 59100 | H18: =SUM(H4:H17) -> 78926.75 | I18: =SUM(I4:I17) -> 61100 | J18: =SUM(J4:J17) -> 52325 | ... O18: =SUM(O4:O17) -> 550716.75

Sheet Total Interest earned
A1: Social Shreholders Interest | C1: Interest
A2: Interest Earned | C2: 45658 | D2: 45689 | E2: 45717 | F2: 45748 | G2: 45778 | H2: 45809 | I2: 45839 | J2: 45870 | K2: 45901 | L2: 45931 | M2: 45962 | N2: 45992 | O2: Total Interest
A4: Number | B4: Members Name
A5: 1 | B5: Aibaki Tembo | C5: ='Jan Loan Interest'!P4 -> 403.125 | D5: ='Feb Loan Interest'!P4 -> 2321.758 | E5: ='Mar Loan Interest '!P4 -> 134.88249 | F5: ='Apr Loan Interest'!P4 -> 248.23944 | G5: ='May loan interest'!P4 -> 260.79045 | H5: ='June loan interest '!P4 -> 117.59358 | I5: ='July Loan interest'!P4 -> 203.41727 | J5: ='August Loan Interest'!J4 -> 106.91845 | K5: ='September Loan Interest'!J4 -> 75 | O5: =SUM(C5:N5) -> 3871.7247
A6: 2 | B6: Brian Chilu | C6: ='Jan Loan Interest'!P5 -> 483.75 | D6: ='Feb Loan Interest'!P5 -> 473.82817 | E6: ='Mar Loan Interest '!P5 -> 539.52995 | F6: ='Apr Loan Interest'!P5 -> 992.95775 | G6: ='May loan interest'!P5 -> 920.43688 | H6: ='June loan interest '!P5 -> 705.5615 | I6: ='July Loan interest'!P5 -> 203.41727 | J6: ='August Loan Interest'!J5 -> 106.91845 | K6: ='September Loan Interest'!J5 -> 225 | O6: =SUM(C6:N6) -> 4651.4
A7: 3 | B7: Chilu Nyendwa | C7: ='Jan Loan Interest'!P6 -> 1612.5 | D7: ='Feb Loan Interest'!P6 -> 118.45704 | E7: ='Mar Loan Interest '!P6 -> 134.88249 | F7: ='Apr Loan Interest'!P6 -> 248.23944 | G7: ='May loan interest'!P6 -> 4141.9659 | H7: ='June loan interest '!P6 -> 117.59358 | I7: ='July Loan interest'!P6 -> 203.41727 | J7: ='August Loan Interest'!J6 -> 224.52876 | K7: ='September Loan Interest'!J6 -> 157.5 | O7: =SUM(C7:N7) -> 6959.0845
A8: 4 | B8: Clive Makala | C8: ='Jan Loan Interest'!P7 -> 6450 | D8: ='Feb Loan Interest'!P7 -> 118.45704 | E8: ='Mar Loan Interest '!P7 -> 134.88249 | F8: ='Apr Loan Interest'!P7 -> 248.23944 | G8: ='May loan interest'!P7 -> 153.40615 | H8: ='June loan interest '!P7 -> 705.5615 | I8: ='July Loan interest'!P7 -> 203.41727 | J8: ='August Loan Interest'!J7 -> 106.91845 | K8: ='September Loan Interest'!J7 -> 75 | O8: =SUM(C8:N8) -> 8195.8823
A9: 5 | B9: David Machungwa | C9: ='Jan Loan Interest'!P8 -> 161.25 | D9: ='Feb Loan Interest'!P8 -> 7462.7937 | E9: ='Mar Loan Interest '!P8 -> 134.88249 | F9: ='Apr Loan Interest'!P8 -> 248.23944 | G9: ='May loan interest'!P8 -> 153.40615 | H9: ='June loan interest '!P8 -> 117.59358 | I9: ='July Loan interest'!P8 -> 203.41727 | J9: ='August Loan Interest'!J8 -> 106.91845 | K9: ='September Loan Interest'!J8 -> 2452.5 | O9: =SUM(C9:N9) -> 11041.001
A10: 6 | B10: Kababa Kangwa | C10: ='Jan Loan Interest'!P9 -> 2983.125 | D10: ='Feb Loan Interest'!P9 -> 4915.9673 | E10: ='Mar Loan Interest '!P9 -> 539.52995 | F10: ='Apr Loan Interest'!P9 -> 496.47887 | G10: ='May loan interest'!P9 -> 613.62458 | H10: ='June loan interest '!P9 -> 117.59358 | I10: ='July Loan interest'!P9 -> 203.41727 | J10: ='August Loan Interest'!J9 -> 106.91845 | K10: ='September Loan Interest'!J9 -> 75 | O10: =SUM(C10:N10) -> 10051.655
A11: 7 | B11: Kalenga Kamwendo | C11: ='Jan Loan Interest'!P10 -> 161.25 | D11: ='Feb Loan Interest'!P10 -> 142.14845 | E11: ='Mar Loan Interest '!P10 -> 202.32373 | F11: ='Apr Loan Interest'!P10 -> 273.06338 | G11: ='May loan interest'!P10 -> 260.79045 | H11: ='June loan interest '!P10 -> 117.59358 | I11: ='July Loan interest'!P10 -> 1159.4784 | J11: ='August Loan Interest'!J10 -> 256.60429 | K11: ='September Loan Interest'!J10 -> 75 | O11: =SUM(C11:N11) -> 2648.2523
A12: 8 | B12: Kote Nikoi | C12: ='Jan Loan Interest'!P11 -> 3547.5 | D12: ='Feb Loan Interest'!P11 -> 118.45704 | E12: ='Mar Loan Interest '!P11 -> 134.88249 | F12: ='Apr Loan Interest'!P11 -> 273.06338 | G12: ='May loan interest'!P11 -> 153.40615 | H12: ='June loan interest '!P11 -> 129.35294 | I12: ='July Loan interest'!P11 -> 203.41727 | J12: ='August Loan Interest'!J11 -> 106.91845 | K12: ='September Loan Interest'!J11 -> 75 | O12: =SUM(C12:N12) -> 4741.9977
A13: 9 | B13: Kunda Maliti | C13: ='Jan Loan Interest'!P12 -> 322.5 | D13: ='Feb Loan Interest'!P12 -> 1658.3986 | E13: ='Mar Loan Interest '!P12 -> 2697.6497 | F13: ='Apr Loan Interest'!P12 -> 496.47887 | G13: ='May loan interest'!P12 -> 306.81229 | H13: ='June loan interest '!P12 -> 670.28342 | I13: ='July Loan interest'!P12 -> 956.06115 | J13: ='August Loan Interest'!J12 -> 427.67382 | K13: ='September Loan Interest'!J12 -> 180 | O13: =SUM(C13:N13) -> 7715.8579
A14: 10 | B14: Mapenzi Mweetwa | C14: ='Jan Loan Interest'!P13 -> 161.25 | D14: ='Feb Loan Interest'!P13 -> 201.37697 | E14: ='Mar Loan Interest '!P13 -> 5395.2995 | F14: ='Apr Loan Interest'!P13 -> 248.23944 | G14: ='May loan interest'!P13 -> 153.40615 | H14: ='June loan interest '!P13 -> 117.59358 | I14: ='July Loan interest'!P13 -> 203.41727 | J14: ='August Loan Interest'!J13 -> 106.91845 | K14: ='September Loan Interest'!J13 -> 75 | O14: =SUM(C14:N14) -> 6662.5013
A15: 11 | B15: Musamba Karabasis | C15: ='Jan Loan Interest'!P14 -> 0 | D15: ='Feb Loan Interest'!P14 -> 2333.6037 | E15: ='Mar Loan Interest '!P14 -> 2131.1433 | F15: ='Apr Loan Interest'!P14 -> 2383.0986 | G15: ='May loan interest'!P14 -> 1564.7427 | H15: ='June loan interest '!P14 -> 1199.4545 | I15: ='July Loan interest'!P14 -> 1261.1871 | J15: ='August Loan Interest'!J14 -> 470.4412 | K15: ='September Loan Interest'!J14 -> 465 | O15: =SUM(C15:N15) -> 11808.671
A16: 12 | B16: Osward Nkhoma | C16: ='Jan Loan Interest'!P15 -> 161.25 | D16: ='Feb Loan Interest'!P15 -> 236.91409 | E16: ='Mar Loan Interest '!P15 -> 269.76497 | F16: ='Apr Loan Interest'!P15 -> 496.47887 | G16: ='May loan interest'!P15 -> 368.17475 | H16: ='June loan interest '!P15 -> 117.59358 | I16: ='July Loan interest'!P15 -> 406.83453 | J16: ='August Loan Interest'!J15 -> 213.83691 | K16: ='September Loan Interest'!J15 -> 150 | O16: =SUM(C16:N16) -> 2420.8477
A17: 13 | B17: Tiza Silavwe | C17: ='Jan Loan Interest'!P16 -> 161.25 | D17: ='Feb Loan Interest'!P16 -> 165.83986 | E17: ='Mar Loan Interest '!P16 -> 161.85898 | F17: ='Apr Loan Interest'!P16 -> 397.1831 | G17: ='May loan interest'!P16 -> 184.08738 | H17: ='June loan interest '!P16 -> 164.63102 | I17: ='July Loan interest'!P16 -> 244.10072 | J17: ='August Loan Interest'!J16 -> 149.68584 | K17: ='September Loan Interest'!J16 -> 120 | O17: =SUM(C17:N17) -> 1748.6369
C19: =SUM(C5:C18) -> 16608.75 | D19: =SUM(D5:D17) -> 20268 | E19: =SUM(E5:E17) -> 12611.513 | F19: =SUM(F5:F17) -> 7050 | G19: =SUM(G5:G17) -> 9235.05 | H19: =SUM(H5:H17) -> 4398 | I19: =SUM(I5:I17) -> 5655 | J19: =SUM(J5:J17) -> 2491.2 | K19: =SUM(K5:K17) -> 4200 | O19: =SUM(O5:O18) -> 82517.513

Sheet Penalty interest
A1: Social Shreholders Interest | C1: Penalty and Interest
A2: 45748 | D2: 45748 | E2: 45778 | F2: 45809 | G2: 45839 | H2: 45870 | I2: 45901 | J2: 45931 | K2: 45962 | L2: 45992 | M2: Total Interest
A3: Number | B3: Members Name
A4: 1 | B4: Aibaki Tembo | D4: =$D$21 -> 53.076923 | M4: =SUM(D4:L4) -> 53.076923
A5: 2 | B5: Brian Chilu | D5: =$D$21 -> 53.076923 | M5: =SUM(D5:L5) -> 53.076923
A6: 3 | B6: Chilu Nyendwa | D6: =$D$21 -> 53.076923 | M6: =SUM(D6:L6) -> 53.076923
A7: 4 | B7: Clive Makala | D7: =$D$21 -> 53.076923 | M7: =SUM(D7:L7) -> 53.076923
A8: 5 | B8: David Machungwa | D8: =$D$21 -> 53.076923 | M8: =SUM(D8:L8) -> 53.076923
A9: 6 | B9: Kababa Kangwa | D9: =$D$21 -> 53.076923 | M9: =SUM(D9:L9) -> 53.076923
A10: 7 | B10: Kalenga Kamwendo | D10: =$D$21 -> 53.076923 | M10: =SUM(D10:L10) -> 53.076923
A11: 8 | B11: Kote Nikoi | D11: =$D$21 -> 53.076923 | M11: =SUM(D11:L11) -> 53.076923
A12: 9 | B12: Kunda Maliti | D12: =$D$21 -> 53.076923 | M12: =SUM(D12:L12) -> 53.076923
A13: 10 | B13: Mapenzi Mweetwa | D13: =$D$21 -> 53.076923 | M13: =SUM(D13:L13) -> 53.076923
A14: 11 | B14: Musamba Karabasis | D14: =$D$21 -> 53.076923 | M14: =SUM(D14:L14) -> 53.076923
A15: 12 | B15: Osward Nkhoma | D15: =$D$21 -> 53.076923 | M15: =SUM(D15:L15) -> 53.076923
A16: 13 | B16: Tiza Silavwe | D16: =$D$21 -> 53.076923 | M16: =SUM(D16:L16) -> 53.076923
B18: Penalties | D18: =Declarations!H75 -> 600 | E18: =SUM(E4:E17) -> 0 | F18: =SUM(F4:F17) -> 0 | G18: =SUM(G4:G17) -> 0 | H18: =SUM(H4:H17) -> 0 | I18: =SUM(I4:I17) -> 0 | J18: =SUM(J4:J17) -> 0 | K18: =SUM(K4:K17) -> 0 | M18: =SUM(M4:M17) -> 690
B19: Interest | D19: =D18*0.15 -> 90
B20: Total penalties + interest | D20: =SUM(D18:D19) -> 690
B21: Split | D21: =D20/13 -> 53.076923

Sheet Jan Loan Interest
A1: Social Shreholders Interest | C1: Interest
D2: 45658 | E2: 45689 | F2: 45717 | G2: 45748 | H2: 45778 | I2: 45809 | J2: 45839 | K2: 45870 | L2: 45901 | M2: 45931 | N2: 45962 | O2: 45992 | P2: Total Interest
A3: Number | B3: Members Name
A4: 1 | B4: Aibaki Tembo | C4: =1250 -> 1250 | D4: =C4*0.15 -> 187.5 | E4: =C4/$C$18*$E$23 -> 22.754854 | F4: =C4/$C$18*$F$25 -> 22.663835 | G4: =C4/$C$18*$G$27 -> 24.211165 | H4: =C4/$C$18*$H$29 -> 44.417476 | I4: =C4/$C$18*$I$32 -> 101.57767 | P4: =SUM(D4:O4) -> 403.125
A5: 2 | B5: Brian Chilu | C5: 1500 | D5: =C5*0.15 -> 225 | E5: =C5/$C$18*$E$23 -> 27.305825 | F5: =C5/$C$18*$F$25 -> 27.196602 | G5: =C5/$C$18*$G$27 -> 29.053398 | H5: =C5/$C$18*$H$29 -> 53.300971 | I5: =C5/$C$18*$I$32 -> 121.8932 | P5: =SUM(D5:O5) -> 483.75
A6: 3 | B6: Chilu Nyendwa | C6: 5000 | D6: =C6*0.15 -> 750 | E6: =C6/$C$18*$E$23 -> 91.019417 | F6: =C6/$C$18*$F$25 -> 90.65534 | G6: =C6/$C$18*$G$27 -> 96.84466 | H6: =C6/$C$18*$H$29 -> 177.6699 | I6: =C6/$C$18*$I$32 -> 406.31068 | P6: =SUM(D6:O6) -> 1612.5
A7: 4 | B7: Clive Makala | C7: 20000 | D7: =C7*0.15 -> 3000 | E7: =C7/$C$18*$E$23 -> 364.07767 | F7: =C7/$C$18*$F$25 -> 362.62136 | G7: =C7/$C$18*$G$27 -> 387.37864 | H7: =C7/$C$18*$H$29 -> 710.67961 | I7: =C7/$C$18*$I$32 -> 1625.2427 | P7: =SUM(D7:O7) -> 6450
A8: 5 | B8: David Machungwa | C8: 500 | D8: =C8*0.15 -> 75 | E8: =C8/$C$18*$E$23 -> 9.1019417 | F8: =C8/$C$18*$F$25 -> 9.065534 | G8: =C8/$C$18*$G$27 -> 9.684466 | H8: =C8/$C$18*$H$29 -> 17.76699 | I8: =C8/$C$18*$I$32 -> 40.631068 | P8: =SUM(D8:O8) -> 161.25
A9: 6 | B9: Kababa Kangwa | C9: 9250 | D9: =C9*0.15 -> 1387.5 | E9: =C9/$C$18*$E$23 -> 168.38592 | F9: =C9/$C$18*$F$25 -> 167.71238 | G9: =C9/$C$18*$G$27 -> 179.16262 | H9: =C9/$C$18*$H$29 -> 328.68932 | I9: =C9/$C$18*$I$32 -> 751.67476 | P9: =SUM(D9:O9) -> 2983.125
A10: 7 | B10: Kalenga Kamwendo | C10: 500 | D10: =C10*0.15 -> 75 | E10: =C10/$C$18*$E$23 -> 9.1019417 | F10: =C10/$C$18*$F$25 -> 9.065534 | G10: =C10/$C$18*$G$27 -> 9.684466 | H10: =C10/$C$18*$H$29 -> 17.76699 | I10: =C10/$C$18*$I$32 -> 40.631068 | P10: =SUM(D10:O10) -> 161.25
A11: 8 | B11: Kote Nikoi | C11: 11000 | D11: =C11*0.15 -> 1650 | E11: =C11/$C$18*$E$23 -> 200.24272 | F11: =C11/$C$18*$F$25 -> 199.44175 | G11: =C11/$C$18*$G$27 -> 213.05825 | H11: =C11/$C$18*$H$29 -> 390.87379 | I11: =C11/$C$18*$I$32 -> 893.8835 | P11: =SUM(D11:O11) -> 3547.5
A12: 9 | B12: Kunda Maliti | C12: 1000 | D12: =C12*0.15 -> 150 | E12: =C12/$C$18*$E$23 -> 18.203883 | F12: =C12/$C$18*$F$25 -> 18.131068 | G12: =C12/$C$18*$G$27 -> 19.368932 | H12: =C12/$C$18*$H$29 -> 35.533981 | I12: =C12/$C$18*$I$32 -> 81.262136 | P12: =SUM(D12:O12) -> 322.5
A13: 10 | B13: Mapenzi Mweetwa | C13: 500 | D13: =C13*0.15 -> 75 | E13: =C13/$C$18*$E$23 -> 9.1019417 | F13: =C13/$C$18*$F$25 -> 9.065534 | G13: =C13/$C$18*$G$27 -> 9.684466 | H13: =C13/$C$18*$H$29 -> 17.76699 | I13: =C13/$C$18*$I$32 -> 40.631068 | P13: =SUM(D13:O13) -> 161.25
A14: 11 | B14: Musamba Karabasis | C14: 0 | D14: =C14*0.15 -> 0 | E14: =C14/$C$18*$E$23 -> 0 | F14: =C14/$C$18*$F$25 -> 0 | G14: =C14/$C$18*$G$27 -> 0 | H14: =C14/$C$18*$H$29 -> 0 | I14: =C14/$C$18*$I$32 -> 0 | P14: =SUM(D14:O14) -> 0
A15: 12 | B15: Osward Nkhoma | C15: 500 | D15: =C15*0.15 -> 75 | E15: =C15/$C$18*$E$23 -> 9.1019417 | F15: =C15/$C$18*$F$25 -> 9.065534 | G15: =C15/$C$18*$G$27 -> 9.684466 | H15: =C15/$C$18*$H$29 -> 17.76699 | I15: =C15/$C$18*$I$32 -> 40.631068 | P15: =SUM(D15:O15) -> 161.25
A16: 13 | B16: Tiza Silavwe | C16: 500 | D16: =C16*0.15 -> 75 | E16: =C16/$C$18*$E$23 -> 9.1019417 | F16: =C16/$C$18*$F$25 -> 9.065534 | G16: =C16/$C$18*$G$27 -> 9.684466 | H16: =C16/$C$18*$H$29 -> 17.76699 | I16: =C16/$C$18*$I$32 -> 40.631068 | P16: =SUM(D16:O16) -> 161.25
C18: =SUM(C4:C17) -> 51500 | D18: =SUM(D4:D17) -> 7725 | E18: =SUM(E4:E17) -> 937.5 | F18: =SUM(F4:F17) -> 933.75 | G18: =SUM(G4:G17) -> 997.5 | H18: =SUM(H4:H17) -> 1830 | I18: =SUM(I4:I17) -> 4185 | J18: =SUM(J4:J17) -> 0 | ... N18: =SUM(N4:N17) -> 0 | P18: =SUM(P4:P17) -> 16608.75
A21: Jan Loan | D21: 51500
A22: Jan repaymenrts | E22: =Declarations!D37 -> 6250
E23: =E22*0.15 -> 937.5
A24: February repayements | F24: =Declarations!D56 -> 6225
F25: =F24*0.15 -> 933.75
A26: March Repayments | G26: =Declarations!D75 -> 6650
G27: =G26*0.15 -> 997.5
A28: April Repayments | H28: =Declarations!D94 -> 12200
H29: =H28*0.15 -> 1830
A31: May Repayments | I31: =Declarations!D112 -> 27900
I32: =I31*0.15 -> 4185

Sheet Feb Loan Interest
A1: Social Shreholders Interest | C1: Interest
D2: 45658 | E2: 45689 | F2: 45717 | G2: 45748 | H2: 45778 | I2: 45809 | J2: 45839 | K2: 45870 | L2: 45901 | M2: 45931 | N2: 45962 | O2: 45992 | P2: Total Interest
A3: Number | B3: Members Name
A4: 1 | B4: Aibaki Tembo | C4: 9800 | E4: =C4*0.15 -> 1470 | F4: =C4/$C$18*$F$22 -> 130.07481 | G4: =C4/$C$18*$G$24 -> 99.661017 | H4: =C4/$C$18*$H$26 -> 99.661017 | I4: =C4/$C$18*$I$28 -> 99.661017 | J4: =C4/$C$18*$J$30 -> 302.41964 | K4: =C4/$C$18*$K$32 -> 60.140269 | L4: =C4/$C$18*$L$34 -> 60.140269 | P4: =SUM(D4:O4) -> 2321.758
A5: 2 | B5: Brian Chilu | C5: 2000 | E5: =C5*0.15 -> 300 | F5: =C5/$C$18*$F$22 -> 26.54588 | G5: =C5/$C$18*$G$24 -> 20.338983 | H5: =C5/$C$18*$H$26 -> 20.338983 | I5: =C5/$C$18*$I$28 -> 20.338983 | J5: =C5/$C$18*$J$30 -> 61.718293 | K5: =C5/$C$18*$K$32 -> 12.273524 | L5: =C5/$C$18*$L$34 -> 12.273524 | P5: =SUM(D5:O5) -> 473.82817
A6: 3 | B6: Chilu Nyendwa | C6: 500 | E6: =C6*0.15 -> 75 | F6: =C6/$C$18*$F$22 -> 6.6364699 | G6: =C6/$C$18*$G$24 -> 5.0847458 | H6: =C6/$C$18*$H$26 -> 5.0847458 | I6: =C6/$C$18*$I$28 -> 5.0847458 | J6: =C6/$C$18*$J$30 -> 15.429573 | K6: =C6/$C$18*$K$32 -> 3.0683811 | L6: =C6/$C$18*$L$34 -> 3.0683811 | P6: =SUM(D6:O6) -> 118.45704
A7: 4 | B7: Clive Makala | C7: 500 | E7: =C7*0.15 -> 75 | F7: =C7/$C$18*$F$22 -> 6.6364699 | G7: =C7/$C$18*$G$24 -> 5.0847458 | H7: =C7/$C$18*$H$26 -> 5.0847458 | I7: =C7/$C$18*$I$28 -> 5.0847458 | J7: =C7/$C$18*$J$30 -> 15.429573 | K7: =C7/$C$18*$K$32 -> 3.0683811 | L7: =C7/$C$18*$L$34 -> 3.0683811 | P7: =SUM(D7:O7) -> 118.45704
A8: 5 | B8: David Machungwa | C8: 31500 | E8: =C8*0.15 -> 4725 | F8: =C8/$C$18*$F$22 -> 418.0976 | G8: =C8/$C$18*$G$24 -> 320.33898 | H8: =C8/$C$18*$H$26 -> 320.33898 | I8: =C8/$C$18*$I$28 -> 320.33898 | J8: =C8/$C$18*$J$30 -> 972.06312 | K8: =C8/$C$18*$K$32 -> 193.30801 | L8: =C8/$C$18*$L$34 -> 193.30801 | P8: =SUM(D8:O8) -> 7462.7937
A9: 6 | B9: Kababa Kangwa | C9: 20750 | E9: =C9*0.15 -> 3112.5 | F9: =C9/$C$18*$F$22 -> 275.4135 | G9: =C9/$C$18*$G$24 -> 211.01695 | H9: =C9/$C$18*$H$26 -> 211.01695 | I9: =C9/$C$18*$I$28 -> 211.01695 | J9: =C9/$C$18*$J$30 -> 640.32729 | K9: =C9/$C$18*$K$32 -> 127.33781 | L9: =C9/$C$18*$L$34 -> 127.33781 | P9: =SUM(D9:O9) -> 4915.9673
A10: 7 | B10: Kalenga Kamwendo | C10: 600 | E10: =C10*0.15 -> 90 | F10: =C10/$C$18*$F$22 -> 7.9637639 | G10: =C10/$C$18*$G$24 -> 6.1016949 | H10: =C10/$C$18*$H$26 -> 6.1016949 | I10: =C10/$C$18*$I$28 -> 6.1016949 | J10: =C10/$C$18*$J$30 -> 18.515488 | K10: =C10/$C$18*$K$32 -> 3.6820573 | L10: =C10/$C$18*$L$34 -> 3.6820573 | P10: =SUM(D10:O10) -> 142.14845
A11: 8 | B11: Kote Nikoi | C11: 500 | E11: =C11*0.15 -> 75 | F11: =C11/$C$18*$F$22 -> 6.6364699 | G11: =C11/$C$18*$G$24 -> 5.0847458 | H11: =C11/$C$18*$H$26 -> 5.0847458 | I11: =C11/$C$18*$I$28 -> 5.0847458 | J11: =C11/$C$18*$J$30 -> 15.429573 | K11: =C11/$C$18*$K$32 -> 3.0683811 | L11: =C11/$C$18*$L$34 -> 3.0683811 | P11: =SUM(D11:O11) -> 118.45704
A12: 9 | B12: Kunda Maliti | C12: 7000 | E12: =C12*0.15 -> 1050 | F12: =C12/$C$18*$F$22 -> 92.910579 | G12: =C12/$C$18*$G$24 -> 71.186441 | H12: =C12/$C$18*$H$26 -> 71.186441 | I12: =C12/$C$18*$I$28 -> 71.186441 | J12: =C12/$C$18*$J$30 -> 216.01403 | K12: =C12/$C$18*$K$32 -> 42.957335 | L12: =C12/$C$18*$L$34 -> 42.957335 | P12: =SUM(D12:O12) -> 1658.3986
A13: 10 | B13: Mapenzi Mweetwa | C13: 850 | E13: =C13*0.15 -> 127.5 | F13: =C13/$C$18*$F$22 -> 11.281999 | G13: =C13/$C$18*$G$24 -> 8.6440678 | H13: =C13/$C$18*$H$26 -> 8.6440678 | I13: =C13/$C$18*$I$28 -> 8.6440678 | J13: =C13/$C$18*$J$30 -> 26.230275 | K13: =C13/$C$18*$K$32 -> 5.2162478 | L13: =C13/$C$18*$L$34 -> 5.2162478 | P13: =SUM(D13:O13) -> 201.37697
A14: 11 | B14: Musamba Karabasis | C14: 9850 | E14: =C14*0.15 -> 1477.5 | F14: =C14/$C$18*$F$22 -> 130.73846 | G14: =C14/$C$18*$G$24 -> 100.16949 | H14: =C14/$C$18*$H$26 -> 100.16949 | I14: =C14/$C$18*$I$28 -> 100.16949 | J14: =C14/$C$18*$J$30 -> 303.96259 | K14: =C14/$C$18*$K$32 -> 60.447107 | L14: =C14/$C$18*$L$34 -> 60.447107 | P14: =SUM(D14:O14) -> 2333.6037
A15: 12 | B15: Osward Nkhoma | C15: 1000 | E15: =C15*0.15 -> 150 | F15: =C15/$C$18*$F$22 -> 13.27294 | G15: =C15/$C$18*$G$24 -> 10.169492 | H15: =C15/$C$18*$H$26 -> 10.169492 | I15: =C15/$C$18*$I$28 -> 10.169492 | J15: =C15/$C$18*$J$30 -> 30.859147 | K15: =C15/$C$18*$K$32 -> 6.1367621 | L15: =C15/$C$18*$L$34 -> 6.1367621 | P15: =SUM(D15:O15) -> 236.91409
A16: 13 | B16: Tiza Silavwe | C16: 700 | E16: =C16*0.15 -> 105 | F16: =C16/$C$18*$F$22 -> 9.2910579 | G16: =C16/$C$18*$G$24 -> 7.1186441 | H16: =C16/$C$18*$H$26 -> 7.1186441 | I16: =C16/$C$18*$I$28 -> 7.1186441 | J16: =C16/$C$18*$J$30 -> 21.601403 | K16: =C16/$C$18*$K$32 -> 4.2957335 | L16: =C16/$C$18*$L$34 -> 4.2957335 | P16: =SUM(D16:O16) -> 165.83986
C18: =SUM(C4:C17) -> 85550 | D18: =SUM(D4:D17) -> 0 | E18: =SUM(E4:E17) -> 12832.5 | F18: =SUM(F4:F17) -> 1135.5 | G18: =SUM(G4:G17) -> 870 | H18: =SUM(H4:H17) -> 870 | I18: =SUM(I4:I17) -> 870 | J18: =SUM(J4:J17) -> 2640 | ... N18: =SUM(N4:N17) -> 0 | P18: =SUM(P4:P17) -> 20268
A21: February repayments | F21: =Declarations!E56 -> 7570
F22: =F21*0.15 -> 1135.5
A23: March Repayments | G23: =Declarations!E75 -> 5800
G24: =G23*0.15 -> 870
A25: April Repayments | H25: =Declarations!E94 -> 5800
H26: =H25*0.15 -> 870
A27: May Repayments | I27: =Declarations!E112 -> 5800
I28: =I27*0.15 -> 870
A29: June Repayments | J29: =Declarations!E132 -> 17600
J30: =J29*0.15 -> 2640
A31: July Repayments | K31: =Declarations!D153 -> 3500
K32: =K31*0.15 -> 525
A33: Aug Repyaments | L33: =Declarations!D173 -> 3500
L34: =L33*0.15 -> 525

Sheet Mar Loan Interest 
A1: Social Shreholders Interest | C1: Interest
D2: 45658 | E2: 45689 | F2: 45717 | G2: 45748 | H2: 45778 | I2: 45809 | J2: 45839 | K2: 45870 | L2: 45901 | M2: 45931 | N2: 45962 | O2: 45992 | P2: Total Interest
A3: Number | B3: Members Name
A4: 1 | B4: Aibaki Tembo | C4: 500 | F4: =C4*0.15 -> 75 | G4: =C4/$C$18*$G$22 -> 6.0160428 | H4: =C4/$C$18*$H$24 -> 4.5721925 | I4: =C4/$C$18*$I$26 -> 16.647193 | J4: =C4/$C$18*$J$28 -> 12.032086 | K4: =C4/$C$18*$K$30 -> 12.593583 | L4: =C4/$C$18*$L$32 -> 8.0213904 | P4: =SUM(D4:O4) -> 134.88249
A5: 2 | B5: Brian Chilu | C5: 2000 | F5: =C5*0.15 -> 300 | G5: =C5/$C$18*$G$22 -> 24.064171 | H5: =C5/$C$18*$H$24 -> 18.28877 | I5: =C5/$C$18*$I$26 -> 66.58877 | J5: =C5/$C$18*$J$28 -> 48.128342 | K5: =C5/$C$18*$K$30 -> 50.374332 | L5: =C5/$C$18*$L$32 -> 32.085561 | P5: =SUM(D5:O5) -> 539.52995
A6: 3 | B6: Chilu Nyendwa | C6: 500 | F6: =C6*0.15 -> 75 | G6: =C6/$C$18*$G$22 -> 6.0160428 | H6: =C6/$C$18*$H$24 -> 4.5721925 | I6: =C6/$C$18*$I$26 -> 16.647193 | J6: =C6/$C$18*$J$28 -> 12.032086 | K6: =C6/$C$18*$K$30 -> 12.593583 | L6: =C6/$C$18*$L$32 -> 8.0213904 | P6: =SUM(D6:O6) -> 134.88249
A7: 4 | B7: Clive Makala | C7: 500 | F7: =C7*0.15 -> 75 | G7: =C7/$C$18*$G$22 -> 6.0160428 | H7: =C7/$C$18*$H$24 -> 4.5721925 | I7: =C7/$C$18*$I$26 -> 16.647193 | J7: =C7/$C$18*$J$28 -> 12.032086 | K7: =C7/$C$18*$K$30 -> 12.593583 | L7: =C7/$C$18*$L$32 -> 8.0213904 | P7: =SUM(D7:O7) -> 134.88249
A8: 5 | B8: David Machungwa | C8: 500 | F8: =C8*0.15 -> 75 | G8: =C8/$C$18*$G$22 -> 6.0160428 | H8: =C8/$C$18*$H$24 -> 4.5721925 | I8: =C8/$C$18*$I$26 -> 16.647193 | J8: =C8/$C$18*$J$28 -> 12.032086 | K8: =C8/$C$18*$K$30 -> 12.593583 | L8: =C8/$C$18*$L$32 -> 8.0213904 | P8: =SUM(D8:O8) -> 134.88249
A9: 6 | B9: Kababa Kangwa | C9: 2000 | F9: =C9*0.15 -> 300 | G9: =C9/$C$18*$G$22 -> 24.064171 | H9: =C9/$C$18*$H$24 -> 18.28877 | I9: =C9/$C$18*$I$26 -> 66.58877 | J9: =C9/$C$18*$J$28 -> 48.128342 | K9: =C9/$C$18*$K$30 -> 50.374332 | L9: =C9/$C$18*$L$32 -> 32.085561 | P9: =SUM(D9:O9) -> 539.52995
A10: 7 | B10: Kalenga Kamwendo | C10: 750 | F10: =C10*0.15 -> 112.5 | G10: =C10/$C$18*$G$22 -> 9.0240642 | H10: =C10/$C$18*$H$24 -> 6.8582888 | I10: =C10/$C$18*$I$26 -> 24.970789 | J10: =C10/$C$18*$J$28 -> 18.048128 | K10: =C10/$C$18*$K$30 -> 18.890374 | L10: =C10/$C$18*$L$32 -> 12.032086 | P10: =SUM(D10:O10) -> 202.32373
A11: 8 | B11: Kote Nikoi | C11: 500 | F11: =C11*0.15 -> 75 | G11: =C11/$C$18*$G$22 -> 6.0160428 | H11: =C11/$C$18*$H$24 -> 4.5721925 | I11: =C11/$C$18*$I$26 -> 16.647193 | J11: =C11/$C$18*$J$28 -> 12.032086 | K11: =C11/$C$18*$K$30 -> 12.593583 | L11: =C11/$C$18*$L$32 -> 8.0213904 | P11: =SUM(D11:O11) -> 134.88249
A12: 9 | B12: Kunda Maliti | C12: 10000 | F12: =C12*0.15 -> 1500 | G12: =C12/$C$18*$G$22 -> 120.32086 | H12: =C12/$C$18*$H$24 -> 91.44385 | I12: =C12/$C$18*$I$26 -> 332.94385 | J12: =C12/$C$18*$J$28 -> 240.64171 | K12: =C12/$C$18*$K$30 -> 251.87166 | L12: =C12/$C$18*$L$32 -> 160.42781 | P12: =SUM(D12:O12) -> 2697.6497
A13: 10 | B13: Mapenzi Mweetwa | C13: 20000 | F13: =C13*0.15 -> 3000 | G13: =C13/$C$18*$G$22 -> 240.64171 | H13: =C13/$C$18*$H$24 -> 182.8877 | I13: =C13/$C$18*$I$26 -> 665.8877 | J13: =C13/$C$18*$J$28 -> 481.28342 | K13: =C13/$C$18*$K$30 -> 503.74332 | L13: =C13/$C$18*$L$32 -> 320.85561 | P13: =SUM(D13:O13) -> 5395.2995
A14: 11 | B14: Musamba Karabasis | C14: 7900 | F14: =C14*0.15 -> 1185 | G14: =C14/$C$18*$G$22 -> 95.053476 | H14: =C14/$C$18*$H$24 -> 72.240642 | I14: =C14/$C$18*$I$26 -> 263.02564 | J14: =C14/$C$18*$J$28 -> 190.10695 | K14: =C14/$C$18*$K$30 -> 198.97861 | L14: =C14/$C$18*$L$32 -> 126.73797 | P14: =SUM(D14:O14) -> 2131.1433
A15: 12 | B15: Osward Nkhoma | C15: 1000 | F15: =C15*0.15 -> 150 | G15: =C15/$C$18*$G$22 -> 12.032086 | H15: =C15/$C$18*$H$24 -> 9.144385 | I15: =C15/$C$18*$I$26 -> 33.294385 | J15: =C15/$C$18*$J$28 -> 24.064171 | K15: =C15/$C$18*$K$30 -> 25.187166 | L15: =C15/$C$18*$L$32 -> 16.042781 | P15: =SUM(D15:O15) -> 269.76497
A16: 13 | B16: Tiza Silavwe | C16: 600 | F16: =C16*0.15 -> 90 | G16: =C16/$C$18*$G$22 -> 7.2192513 | H16: =C16/$C$18*$H$24 -> 5.486631 | I16: =C16/$C$18*$I$26 -> 19.976631 | J16: =C16/$C$18*$J$28 -> 14.438503 | K16: =C16/$C$18*$K$30 -> 15.112299 | L16: =C16/$C$18*$L$32 -> 9.6256684 | P16: =SUM(D16:O16) -> 161.85898
C18: =SUM(C4:C17) -> 46750 | D18: =SUM(D4:D17) -> 0 | E18: =SUM(E4:E17) -> 0 | F18: =SUM(F4:F17) -> 7012.5 | G18: =SUM(G4:G17) -> 562.5 | H18: =SUM(H4:H17) -> 427.5 | I18: =SUM(I4:I17) -> 1556.5125 | J18: =SUM(J4:J17) -> 1125 | ... N18: =SUM(N4:N17) -> 0 | P18: =SUM(P4:P17) -> 12611.513
A21: March repayments | G21: =Declarations!F75 -> 3750
G22: =G21*0.15 -> 562.5
A23: April repayments | H23: =Declarations!F94 -> 2850
H24: =H23*0.15 -> 427.5
A25: May Repayements | I25: =Declarations!F112 -> 10376.75
I26: =I25*0.15 -> 1556.5125
A27: June Repayments | J27: =Declarations!F132 -> 7500
J28: =J27*0.15 -> 1125
A29: July Repayments | K29: =Declarations!E153 -> 7850
K30: =K29*0.15 -> 1177.5
A31: August Repayments | L31: =Declarations!E173 -> 5000
L32: =L31*0.15 -> 750

Sheet Apr Loan Interest
A1: Social Shreholders Interest | C1: Interest
A2: 45748 | D2: 45658 | E2: 45689 | F2: 45717 | G2: 45748 | H2: 45778 | I2: 45809 | J2: 45839 | K2: 45870 | L2: 45901 | M2: 45931 | N2: 45962 | O2: 45992 | P2: Total Interest
A3: Number | B3: Members Name
A4: 1 | B4: Aibaki Tembo | C4: 500 | G4: =C4*0.15 -> 75 | H4: =C4/$C$18*$H$21 -> 43.045775 | I4: =C4/$C$18*$I$23 -> 49.911972 | J4: =C4/$C$18*$J$25 -> 51.496479 | K4: =C4/$C$18*$K$27 -> 24.401408 | L4: =C4/$C$18*$L$29 -> 4.3838028 | P4: =SUM(D4:O4) -> 248.23944
A5: 2 | B5: Brian Chilu | C5: 2000 | G5: =C5*0.15 -> 300 | H5: =C5/$C$18*$H$21 -> 172.1831 | I5: =C5/$C$18*$I$23 -> 199.64789 | J5: =C5/$C$18*$J$25 -> 205.98592 | K5: =C5/$C$18*$K$27 -> 97.605634 | L5: =C5/$C$18*$L$29 -> 17.535211 | P5: =SUM(D5:O5) -> 992.95775
A6: 3 | B6: Chilu Nyendwa | C6: 500 | G6: =C6*0.15 -> 75 | H6: =C6/$C$18*$H$21 -> 43.045775 | I6: =C6/$C$18*$I$23 -> 49.911972 | J6: =C6/$C$18*$J$25 -> 51.496479 | K6: =C6/$C$18*$K$27 -> 24.401408 | L6: =C6/$C$18*$L$29 -> 4.3838028 | P6: =SUM(D6:O6) -> 248.23944
A7: 4 | B7: Clive Makala | C7: 500 | G7: =C7*0.15 -> 75 | H7: =C7/$C$18*$H$21 -> 43.045775 | I7: =C7/$C$18*$I$23 -> 49.911972 | J7: =C7/$C$18*$J$25 -> 51.496479 | K7: =C7/$C$18*$K$27 -> 24.401408 | L7: =C7/$C$18*$L$29 -> 4.3838028 | P7: =SUM(D7:O7) -> 248.23944
A8: 5 | B8: David Machungwa | C8: 500 | G8: =C8*0.15 -> 75 | H8: =C8/$C$18*$H$21 -> 43.045775 | I8: =C8/$C$18*$I$23 -> 49.911972 | J8: =C8/$C$18*$J$25 -> 51.496479 | K8: =C8/$C$18*$K$27 -> 24.401408 | L8: =C8/$C$18*$L$29 -> 4.3838028 | P8: =SUM(D8:O8) -> 248.23944
A9: 6 | B9: Kababa Kangwa | C9: 1000 | G9: =C9*0.15 -> 150 | H9: =C9/$C$18*$H$21 -> 86.091549 | I9: =C9/$C$18*$I$23 -> 99.823944 | J9: =C9/$C$18*$J$25 -> 102.99296 | K9: =C9/$C$18*$K$27 -> 48.802817 | L9: =C9/$C$18*$L$29 -> 8.7676056 | P9: =SUM(D9:O9) -> 496.47887
A10: 7 | B10: Kalenga Kamwendo | C10: 550 | G10: =C10*0.15 -> 82.5 | H10: =C10/$C$18*$H$21 -> 47.350352 | I10: =C10/$C$18*$I$23 -> 54.903169 | J10: =C10/$C$18*$J$25 -> 56.646127 | K10: =C10/$C$18*$K$27 -> 26.841549 | L10: =C10/$C$18*$L$29 -> 4.8221831 | P10: =SUM(D10:O10) -> 273.06338
A11: 8 | B11: Kote Nikoi | C11: 550 | G11: =C11*0.15 -> 82.5 | H11: =C11/$C$18*$H$21 -> 47.350352 | I11: =C11/$C$18*$I$23 -> 54.903169 | J11: =C11/$C$18*$J$25 -> 56.646127 | K11: =C11/$C$18*$K$27 -> 26.841549 | L11: =C11/$C$18*$L$29 -> 4.8221831 | P11: =SUM(D11:O11) -> 273.06338
A12: 9 | B12: Kunda Maliti | C12: 1000 | G12: =C12*0.15 -> 150 | H12: =C12/$C$18*$H$21 -> 86.091549 | I12: =C12/$C$18*$I$23 -> 99.823944 | J12: =C12/$C$18*$J$25 -> 102.99296 | K12: =C12/$C$18*$K$27 -> 48.802817 | L12: =C12/$C$18*$L$29 -> 8.7676056 | P12: =SUM(D12:O12) -> 496.47887
A13: 10 | B13: Mapenzi Mweetwa | C13: 500 | G13: =C13*0.15 -> 75 | H13: =C13/$C$18*$H$21 -> 43.045775 | I13: =C13/$C$18*$I$23 -> 49.911972 | J13: =C13/$C$18*$J$25 -> 51.496479 | K13: =C13/$C$18*$K$27 -> 24.401408 | L13: =C13/$C$18*$L$29 -> 4.3838028 | P13: =SUM(D13:O13) -> 248.23944
A14: 11 | B14: Musamba Karabasis | C14: 4800 | G14: =C14*0.15 -> 720 | H14: =C14/$C$18*$H$21 -> 413.23944 | I14: =C14/$C$18*$I$23 -> 479.15493 | J14: =C14/$C$18*$J$25 -> 494.3662 | K14: =C14/$C$18*$K$27 -> 234.25352 | L14: =C14/$C$18*$L$29 -> 42.084507 | P14: =SUM(D14:O14) -> 2383.0986
A15: 12 | B15: Osward Nkhoma | C15: 1000 | G15: =C15*0.15 -> 150 | H15: =C15/$C$18*$H$21 -> 86.091549 | I15: =C15/$C$18*$I$23 -> 99.823944 | J15: =C15/$C$18*$J$25 -> 102.99296 | K15: =C15/$C$18*$K$27 -> 48.802817 | L15: =C15/$C$18*$L$29 -> 8.7676056 | P15: =SUM(D15:O15) -> 496.47887
A16: 13 | B16: Tiza Silavwe | C16: 800 | G16: =C16*0.15 -> 120 | H16: =C16/$C$18*$H$21 -> 68.873239 | I16: =C16/$C$18*$I$23 -> 79.859155 | J16: =C16/$C$18*$J$25 -> 82.394366 | K16: =C16/$C$18*$K$27 -> 39.042254 | L16: =C16/$C$18*$L$29 -> 7.0140845 | P16: =SUM(D16:O16) -> 397.1831
C18: =SUM(C4:C17) -> 14200 | D18: =SUM(D4:D17) -> 0 | E18: =SUM(E4:E17) -> 0 | F18: =SUM(F4:F17) -> 0 | G18: =SUM(G4:G17) -> 2130 | H18: =SUM(H4:H17) -> 1222.5 | I18: =SUM(I4:I17) -> 1417.5 | J18: =SUM(J4:J17) -> 1462.5 | ... N18: =SUM(N4:N17) -> 0 | P18: =SUM(P4:P17) -> 7050
B20: April repayments | H20: =Declarations!G94 -> 8150
H21: =H20*0.15 -> 1222.5
B22: May Repayments | I22: =Declarations!G112 -> 9450
I23: =I22*0.15 -> 1417.5
B24: June Repayments | J24: =Declarations!G132 -> 9750
J25: =J24*0.15 -> 1462.5
B26: July Repayments | K26: =Declarations!F153 -> 4620
K27: =K26*0.15 -> 693
L28: =Declarations!F173 -> 830
L29: =L28*0.15 -> 124.5

Sheet May loan interest
A1: Social Shreholders Interest | C1: Interest
A2: 45778 | D2: 45658 | E2: 45689 | F2: 45717 | G2: 45748 | H2: 45778 | I2: 45809 | J2: 45839 | K2: 45870 | L2: 45901 | M2: 45931 | N2: 45962 | O2: 45992 | P2: Total Interest
A3: Number | B3: Members Name
A4: 1 | B4: Aibaki Tembo | C4: 850 | H4: =C4*0.15 -> 127.5 | I4: =C4/$C$18*$I$21 -> 28.380399 | J4: =C4/$C$18*$J$23 -> 47.44186 | K4: =C4/$C$18*$K$25 -> 37.699336 | L4: =C4/$C$18*$L$27 -> 19.768854 | P4: =SUM(D4:O4) -> 260.79045
A5: 2 | B5: Brian Chilu | C5: 3000 | H5: =C5*0.15 -> 450 | I5: =C5/$C$18*$I$21 -> 100.16611 | J5: =C5/$C$18*$J$23 -> 167.44186 | K5: =C5/$C$18*$K$25 -> 133.05648 | L5: =C5/$C$18*$L$27 -> 69.772425 | P5: =SUM(D5:O5) -> 920.43688
A6: 3 | B6: Chilu Nyendwa | C6: =500+13000 -> 13500 | H6: =C6*0.15 -> 2025 | I6: =C6/$C$18*$I$21 -> 450.74751 | J6: =C6/$C$18*$J$23 -> 753.48837 | K6: =C6/$C$18*$K$25 -> 598.75415 | L6: =C6/$C$18*$L$27 -> 313.97591 | P6: =SUM(D6:O6) -> 4141.9659
A7: 4 | B7: Clive Makala | C7: 500 | H7: =C7*0.15 -> 75 | I7: =C7/$C$18*$I$21 -> 16.694352 | J7: =C7/$C$18*$J$23 -> 27.906977 | K7: =C7/$C$18*$K$25 -> 22.17608 | L7: =C7/$C$18*$L$27 -> 11.628738 | P7: =SUM(D7:O7) -> 153.40615
A8: 5 | B8: David Machungwa | C8: 500 | H8: =C8*0.15 -> 75 | I8: =C8/$C$18*$I$21 -> 16.694352 | J8: =C8/$C$18*$J$23 -> 27.906977 | K8: =C8/$C$18*$K$25 -> 22.17608 | L8: =C8/$C$18*$L$27 -> 11.628738 | P8: =SUM(D8:O8) -> 153.40615
A9: 6 | B9: Kababa Kangwa | C9: 2000 | H9: =C9*0.15 -> 300 | I9: =C9/$C$18*$I$21 -> 66.777409 | J9: =C9/$C$18*$J$23 -> 111.62791 | K9: =C9/$C$18*$K$25 -> 88.704319 | L9: =C9/$C$18*$L$27 -> 46.51495 | P9: =SUM(D9:O9) -> 613.62458
A10: 7 | B10: Kalenga Kamwendo | C10: 850 | H10: =C10*0.15 -> 127.5 | I10: =C10/$C$18*$I$21 -> 28.380399 | J10: =C10/$C$18*$J$23 -> 47.44186 | K10: =C10/$C$18*$K$25 -> 37.699336 | L10: =C10/$C$18*$L$27 -> 19.768854 | P10: =SUM(D10:O10) -> 260.79045
A11: 8 | B11: Kote Nikoi | C11: 500 | H11: =C11*0.15 -> 75 | I11: =C11/$C$18*$I$21 -> 16.694352 | J11: =C11/$C$18*$J$23 -> 27.906977 | K11: =C11/$C$18*$K$25 -> 22.17608 | L11: =C11/$C$18*$L$27 -> 11.628738 | P11: =SUM(D11:O11) -> 153.40615
A12: 9 | B12: Kunda Maliti | C12: 1000 | H12: =C12*0.15 -> 150 | I12: =C12/$C$18*$I$21 -> 33.388704 | J12: =C12/$C$18*$J$23 -> 55.813953 | K12: =C12/$C$18*$K$25 -> 44.352159 | L12: =C12/$C$18*$L$27 -> 23.257475 | P12: =SUM(D12:O12) -> 306.81229
A13: 10 | B13: Mapenzi Mweetwa | C13: 500 | H13: =C13*0.15 -> 75 | I13: =C13/$C$18*$I$21 -> 16.694352 | J13: =C13/$C$18*$J$23 -> 27.906977 | K13: =C13/$C$18*$K$25 -> 22.17608 | L13: =C13/$C$18*$L$27 -> 11.628738 | P13: =SUM(D13:O13) -> 153.40615
A14: 11 | B14: Musamba Karabasis | C14: 5100 | H14: =C14*0.15 -> 765 | I14: =C14/$C$18*$I$21 -> 170.28239 | J14: =C14/$C$18*$J$23 -> 284.65116 | K14: =C14/$C$18*$K$25 -> 226.19601 | L14: =C14/$C$18*$L$27 -> 118.61312 | P14: =SUM(D14:O14) -> 1564.7427
A15: 12 | B15: Osward Nkhoma | C15: 1200 | H15: =C15*0.15 -> 180 | I15: =C15/$C$18*$I$21 -> 40.066445 | J15: =C15/$C$18*$J$23 -> 66.976744 | K15: =C15/$C$18*$K$25 -> 53.222591 | L15: =C15/$C$18*$L$27 -> 27.90897 | P15: =SUM(D15:O15) -> 368.17475
A16: 13 | B16: Tiza Silavwe | C16: 600 | H16: =C16*0.15 -> 90 | I16: =C16/$C$18*$I$21 -> 20.033223 | J16: =C16/$C$18*$J$23 -> 33.488372 | K16: =C16/$C$18*$K$25 -> 26.611296 | L16: =C16/$C$18*$L$27 -> 13.954485 | P16: =SUM(D16:O16) -> 184.08738
C18: =SUM(C4:C17) -> 30100 | D18: =SUM(D4:D17) -> 0 | E18: =SUM(E4:E17) -> 0 | F18: =SUM(F4:F17) -> 0 | G18: =SUM(G4:G17) -> 0 | H18: =SUM(H4:H17) -> 4515 | I18: =SUM(I4:I17) -> 1005 | J18: =SUM(J4:J17) -> 1680 | ... N18: =SUM(N4:N17) -> 0 | P18: =SUM(P4:P17) -> 9235.05
B20: May Repayments | I20: =Declarations!H112 -> 6700
I21: =I20*0.15 -> 1005
B22: June Repayments | J22: =Declarations!H132 -> 11200
J23: =J22*0.15 -> 1680
B24: July Repayments | K24: =Declarations!G153 -> 8900
K25: =K24*0.15 -> 1335
B26: Aug Repayments | L26: =Declarations!G173 -> 4667
L27: =L26*0.15 -> 700.05

Sheet June loan interest 
A1: Social Shreholders Interest | C1: Interest
A2: 45778 | D2: 45658 | E2: 45689 | F2: 45717 | G2: 45748 | H2: 45778 | I2: 45809 | J2: 45839 | K2: 45870 | L2: 45901 | M2: 45931 | N2: 45962 | O2: 45992 | P2: Total Interest
A3: Number | B3: Members Name
A4: 1 | B4: Aibaki Tembo | C4: 500 | I4: =C4*0.15 -> 75 | J4: =C4/$C$18*$J$21 -> 4.6122995 | K4: =C4/$C$18*$K$23 -> 17.787433 | L4: =C4/$C$18*$L$25 -> 20.19385 | P4: =SUM(D4:O4) -> 117.59358
A5: 2 | B5: Brian Chilu | C5: 3000 | I5: =C5*0.15 -> 450 | J5: =C5/$C$18*$J$21 -> 27.673797 | K5: =C5/$C$18*$K$23 -> 106.7246 | L5: =C5/$C$18*$L$25 -> 121.1631 | P5: =SUM(D5:O5) -> 705.5615
A6: 3 | B6: Chilu Nyendwa | C6: 500 | I6: =C6*0.15 -> 75 | J6: =C6/$C$18*$J$21 -> 4.6122995 | K6: =C6/$C$18*$K$23 -> 17.787433 | L6: =C6/$C$18*$L$25 -> 20.19385 | P6: =SUM(D6:O6) -> 117.59358
A7: 4 | B7: Clive Makala | C7: 3000 | I7: =C7*0.15 -> 450 | J7: =C7/$C$18*$J$21 -> 27.673797 | K7: =C7/$C$18*$K$23 -> 106.7246 | L7: =C7/$C$18*$L$25 -> 121.1631 | P7: =SUM(D7:O7) -> 705.5615
A8: 5 | B8: David Machungwa | C8: 500 | I8: =C8*0.15 -> 75 | J8: =C8/$C$18*$J$21 -> 4.6122995 | K8: =C8/$C$18*$K$23 -> 17.787433 | L8: =C8/$C$18*$L$25 -> 20.19385 | P8: =SUM(D8:O8) -> 117.59358
A9: 6 | B9: Kababa Kangwa | C9: 500 | I9: =C9*0.15 -> 75 | J9: =C9/$C$18*$J$21 -> 4.6122995 | K9: =C9/$C$18*$K$23 -> 17.787433 | L9: =C9/$C$18*$L$25 -> 20.19385 | P9: =SUM(D9:O9) -> 117.59358
A10: 7 | B10: Kalenga Kamwendo | C10: 500 | I10: =C10*0.15 -> 75 | J10: =C10/$C$18*$J$21 -> 4.6122995 | K10: =C10/$C$18*$K$23 -> 17.787433 | L10: =C10/$C$18*$L$25 -> 20.19385 | P10: =SUM(D10:O10) -> 117.59358
A11: 8 | B11: Kote Nikoi | C11: 550 | I11: =C11*0.15 -> 82.5 | J11: =C11/$C$18*$J$21 -> 5.0735294 | K11: =C11/$C$18*$K$23 -> 19.566176 | L11: =C11/$C$18*$L$25 -> 22.213235 | P11: =SUM(D11:O11) -> 129.35294
A12: 9 | B12: Kunda Maliti | C12: 2850 | I12: =C12*0.15 -> 427.5 | J12: =C12/$C$18*$J$21 -> 26.290107 | K12: =C12/$C$18*$K$23 -> 101.38837 | L12: =C12/$C$18*$L$25 -> 115.10495 | P12: =SUM(D12:O12) -> 670.28342
A13: 10 | B13: Mapenzi Mweetwa | C13: 500 | I13: =C13*0.15 -> 75 | J13: =C13/$C$18*$J$21 -> 4.6122995 | K13: =C13/$C$18*$K$23 -> 17.787433 | L13: =C13/$C$18*$L$25 -> 20.19385 | P13: =SUM(D13:O13) -> 117.59358
A14: 11 | B14: Musamba Karabasis | C14: 5100 | I14: =C14*0.15 -> 765 | J14: =C14/$C$18*$J$21 -> 47.045455 | K14: =C14/$C$18*$K$23 -> 181.43182 | L14: =C14/$C$18*$L$25 -> 205.97727 | P14: =SUM(D14:O14) -> 1199.4545
A15: 12 | B15: Osward Nkhoma | C15: 500 | I15: =C15*0.15 -> 75 | J15: =C15/$C$18*$J$21 -> 4.6122995 | K15: =C15/$C$18*$K$23 -> 17.787433 | L15: =C15/$C$18*$L$25 -> 20.19385 | P15: =SUM(D15:O15) -> 117.59358
A16: 13 | B16: Tiza Silavwe | C16: 700 | I16: =C16*0.15 -> 105 | J16: =C16/$C$18*$J$21 -> 6.4572193 | K16: =C16/$C$18*$K$23 -> 24.902406 | L16: =C16/$C$18*$L$25 -> 28.27139 | P16: =SUM(D16:O16) -> 164.63102
C18: =SUM(C4:C17) -> 18700 | D18: =SUM(D4:D17) -> 0 | E18: =SUM(E4:E17) -> 0 | F18: =SUM(F4:F17) -> 0 | G18: =SUM(G4:G17) -> 0 | H18: =SUM(H4:H17) -> 0 | I18: =SUM(I4:I17) -> 2805 | J18: =SUM(J4:J17) -> 172.5 | ... N18: =SUM(N4:N17) -> 0 | P18: =SUM(P4:P17) -> 4398
B20: June Repayments | J20: =Declarations!I132 -> 1150
J21: =J20*0.15 -> 172.5
B22: July Repayments | K22: =Declarations!H153 -> 4435
K23: =K22*0.15 -> 665.25
B24: August Repayments | L24: =Declarations!H173 -> 5035
L25: =L24*0.15 -> 755.25

Sheet July Loan interest
A1: Social Shreholders Interest | C1: Interest
A2: 45778 | D2: 45658 | E2: 45689 | F2: 45717 | G2: 45748 | H2: 45778 | I2: 45809 | J2: 45839 | K2: 45870 | L2: 45901 | M2: 45931 | N2: 45962 | O2: 45992 | P2: Total Interest
A3: Number | B3: Members Name
A4: 1 | B4: Aibaki Tembo | C4: 500 | J4: =C4*0.15 -> 75 | K4: =C4/$C$18*$K$21 -> 61.348921 | L4: =C4/$C$18*$L$23 -> 67.068345 | P4: =SUM(D4:O4) -> 203.41727
A5: 2 | B5: Brian Chilu | C5: 500 | J5: =C5*0.15 -> 75 | K5: =C5/$C$18*$K$21 -> 61.348921 | L5: =C5/$C$18*$L$23 -> 67.068345 | P5: =SUM(D5:O5) -> 203.41727
A6: 3 | B6: Chilu Nyendwa | C6: 500 | J6: =C6*0.15 -> 75 | K6: =C6/$C$18*$K$21 -> 61.348921 | L6: =C6/$C$18*$L$23 -> 67.068345 | P6: =SUM(D6:O6) -> 203.41727
A7: 4 | B7: Clive Makala | C7: 500 | J7: =C7*0.15 -> 75 | K7: =C7/$C$18*$K$21 -> 61.348921 | L7: =C7/$C$18*$L$23 -> 67.068345 | P7: =SUM(D7:O7) -> 203.41727
A8: 5 | B8: David Machungwa | C8: 500 | J8: =C8*0.15 -> 75 | K8: =C8/$C$18*$K$21 -> 61.348921 | L8: =C8/$C$18*$L$23 -> 67.068345 | P8: =SUM(D8:O8) -> 203.41727
A9: 6 | B9: Kababa Kangwa | C9: 500 | J9: =C9*0.15 -> 75 | K9: =C9/$C$18*$K$21 -> 61.348921 | L9: =C9/$C$18*$L$23 -> 67.068345 | P9: =SUM(D9:O9) -> 203.41727
A10: 7 | B10: Kalenga Kamwendo | C10: 2850 | J10: =C10*0.15 -> 427.5 | K10: =C10/$C$18*$K$21 -> 349.68885 | L10: =C10/$C$18*$L$23 -> 382.28957 | P10: =SUM(D10:O10) -> 1159.4784
A11: 8 | B11: Kote Nikoi | C11: 500 | J11: =C11*0.15 -> 75 | K11: =C11/$C$18*$K$21 -> 61.348921 | L11: =C11/$C$18*$L$23 -> 67.068345 | P11: =SUM(D11:O11) -> 203.41727
A12: 9 | B12: Kunda Maliti | C12: 2350 | J12: =C12*0.15 -> 352.5 | K12: =C12/$C$18*$K$21 -> 288.33993 | L12: =C12/$C$18*$L$23 -> 315.22122 | P12: =SUM(D12:O12) -> 956.06115
A13: 10 | B13: Mapenzi Mweetwa | C13: 500 | J13: =C13*0.15 -> 75 | K13: =C13/$C$18*$K$21 -> 61.348921 | L13: =C13/$C$18*$L$23 -> 67.068345 | P13: =SUM(D13:O13) -> 203.41727
A14: 11 | B14: Musamba Karabasis | C14: 3100 | J14: =C14*0.15 -> 465 | K14: =C14/$C$18*$K$21 -> 380.36331 | L14: =C14/$C$18*$L$23 -> 415.82374 | P14: =SUM(D14:O14) -> 1261.1871
A15: 12 | B15: Osward Nkhoma | C15: 1000 | J15: =C15*0.15 -> 150 | K15: =C15/$C$18*$K$21 -> 122.69784 | L15: =C15/$C$18*$L$23 -> 134.13669 | P15: =SUM(D15:O15) -> 406.83453
A16: 13 | B16: Tiza Silavwe | C16: 600 | J16: =C16*0.15 -> 90 | K16: =C16/$C$18*$K$21 -> 73.618705 | L16: =C16/$C$18*$L$23 -> 80.482014 | P16: =SUM(D16:O16) -> 244.10072
C18: =SUM(C4:C17) -> 13900 | D18: =SUM(D4:D17) -> 0 | E18: =SUM(E4:E17) -> 0 | F18: =SUM(F4:F17) -> 0 | G18: =SUM(G4:G17) -> 0 | H18: =SUM(H4:H17) -> 0 | I18: =SUM(I4:I17) -> 0 | J18: =SUM(J4:J17) -> 2085 | ... N18: =SUM(N4:N17) -> 0 | P18: =SUM(P4:P17) -> 5655
B20: July Repayments | K20: =Declarations!I153 -> 11370
K21: =K20*0.15 -> 1705.5
B22: AUG Repayments | L22: =Declarations!I173 -> 12430
L23: =L22*0.15 -> 1864.5

Sheet August Loan Interest
A1: Social Shreholders Interest | C1: Interest
A2: 45870 | D2: 45870 | E2: 45901 | F2: 45931 | G2: 45962 | H2: 45992 | I2: 45992 | J2: Total Interest
A3: Number | B3: Members Name
A4: 1 | B4: Aibaki Tembo | C4: 500 | D4: =C4*0.15 -> 75 | E4: =C4/$C$18*$E$21 -> 31.918455 | J4: =SUM(D4:I4) -> 106.91845
A5: 2 | B5: Brian Chilu | C5: 500 | D5: =C5*0.15 -> 75 | E5: =C5/$C$18*$E$21 -> 31.918455 | J5: =SUM(D5:I5) -> 106.91845
A6: 3 | B6: Chilu Nyendwa | C6: 1050 | D6: =C6*0.15 -> 157.5 | E6: =C6/$C$18*$E$21 -> 67.028755 | J6: =SUM(D6:I6) -> 224.52876
A7: 4 | B7: Clive Makala | C7: 500 | D7: =C7*0.15 -> 75 | E7: =C7/$C$18*$E$21 -> 31.918455 | J7: =SUM(D7:I7) -> 106.91845
A8: 5 | B8: David Machungwa | C8: 500 | D8: =C8*0.15 -> 75 | E8: =C8/$C$18*$E$21 -> 31.918455 | J8: =SUM(D8:I8) -> 106.91845
A9: 6 | B9: Kababa Kangwa | C9: 500 | D9: =C9*0.15 -> 75 | E9: =C9/$C$18*$E$21 -> 31.918455 | J9: =SUM(D9:I9) -> 106.91845 | O9: =C5/$C$18*$L$23 -> 0
A10: 7 | B10: Kalenga Kamwendo | C10: 1200 | D10: =C10*0.15 -> 180 | E10: =C10/$C$18*$E$21 -> 76.604292 | J10: =SUM(D10:I10) -> 256.60429
A11: 8 | B11: Kote Nikoi | C11: 500 | D11: =C11*0.15 -> 75 | E11: =C11/$C$18*$E$21 -> 31.918455 | J11: =SUM(D11:I11) -> 106.91845
A12: 9 | B12: Kunda Maliti | C12: 2000 | D12: =C12*0.15 -> 300 | E12: =C12/$C$18*$E$21 -> 127.67382 | J12: =SUM(D12:I12) -> 427.67382
A13: 10 | B13: Mapenzi Mweetwa | C13: 500 | D13: =C13*0.15 -> 75 | E13: =C13/$C$18*$E$21 -> 31.918455 | J13: =SUM(D13:I13) -> 106.91845
A14: 11 | B14: Musamba Karabasis | C14: 2200 | D14: =C14*0.15 -> 330 | E14: =C14/$C$18*$E$21 -> 140.4412 | J14: =SUM(D14:I14) -> 470.4412
A15: 12 | B15: Osward Nkhoma | C15: 1000 | D15: =C15*0.15 -> 150 | E15: =C15/$C$18*$E$21 -> 63.83691 | J15: =SUM(D15:I15) -> 213.83691
A16: 13 | B16: Tiza Silavwe | C16: 700 | D16: =C16*0.15 -> 105 | E16: =C16/$C$18*$E$21 -> 44.685837 | J16: =SUM(D16:I16) -> 149.68584
C18: =SUM(C4:C17) -> 11650 | D18: =SUM(D4:D17) -> 1747.5 | E18: =SUM(E4:E17) -> 743.7 | F18: =SUM(F4:F17) -> 0 | G18: =SUM(G4:G17) -> 0 | H18: =SUM(H4:H17) -> 0 | J18: =SUM(J4:J17) -> 2491.2
A20: Aug repayment | E20: =Declarations!J173 -> 4958
E21: =E20*0.15 -> 743.7

Sheet September Loan Interest
A1: Social Shreholders Interest | C1: Interest
A2: 45901 | D2: 45901 | E2: 45931 | F2: 45962 | G2: 45992 | J2: Total Interest
A3: Number | B3: Members Name
A4: 1 | B4: Aibaki Tembo | C4: 500 | D4: =C4*0.15 -> 75 | J4: =SUM(D4:I4) -> 75
A5: 2 | B5: Brian Chilu | C5: 1500 | D5: =C5*0.15 -> 225 | J5: =SUM(D5:I5) -> 225
A6: 3 | B6: Chilu Nyendwa | C6: 1050 | D6: =C6*0.15 -> 157.5 | J6: =SUM(D6:I6) -> 157.5
A7: 4 | B7: Clive Makala | C7: 500 | D7: =C7*0.15 -> 75 | J7: =SUM(D7:I7) -> 75
A8: 5 | B8: David Machungwa | C8: 16350 | D8: =C8*0.15 -> 2452.5 | J8: =SUM(D8:I8) -> 2452.5
A9: 6 | B9: Kababa Kangwa | C9: 500 | D9: =C9*0.15 -> 75 | J9: =SUM(D9:I9) -> 75
A10: 7 | B10: Kalenga Kamwendo | C10: 500 | D10: =C10*0.15 -> 75 | J10: =SUM(D10:I10) -> 75
A11: 8 | B11: Kote Nikoi | C11: 500 | D11: =C11*0.15 -> 75 | J11: =SUM(D11:I11) -> 75
A12: 9 | B12: Kunda Maliti | C12: 1200 | D12: =C12*0.15 -> 180 | J12: =SUM(D12:I12) -> 180
A13: 10 | B13: Mapenzi Mweetwa | C13: 500 | D13: =C13*0.15 -> 75 | J13: =SUM(D13:I13) -> 75
A14: 11 | B14: Musamba Karabasis | C14: 3100 | D14: =C14*0.15 -> 465 | J14: =SUM(D14:I14) -> 465
A15: 12 | B15: Osward Nkhoma | C15: 1000 | D15: =C15*0.15 -> 150 | J15: =SUM(D15:I15) -> 150
A16: 13 | B16: Tiza Silavwe | C16: 800 | D16: =C16*0.15 -> 120 | J16: =SUM(D16:I16) -> 120
C18: =SUM(C4:C17) -> 28000 | D18: =SUM(D4:D17) -> 4200 | E18: =SUM(E4:E17) -> 0 | F18: =SUM(F4:F17) -> 0 | G18: =SUM(G4:G17) -> 0 | H18: =SUM(H4:H17) -> 0 | J18: =SUM(J4:J17) -> 4200

Sheet Interest equity
C5: 51500 | D5: 91800 | E5: 60545 | F5: 31000 | G5: 59100 | H5: 78926.75 | I5: 61100
C6: 51500 | D6: 85550 | E6: 46750 | F6: 14200 | G6: 30100 | H6: 18700 | I6: 13900
A7: Jan Repaymenrts | D7: 6250 | E7: 6225 | F7: 6650 | G7: 12200 | H7: 27900 | I7: 17600
A8: Feb Repayments | E8: 7570 | F8: 5800 | G8: 5800 | H8: 5800 | I8: 7500
A9: Mar Repaymenrts | F9: 3750 | G9: 2850 | H9: 10376.75 | I9: 9750
A10: Apr Repayments | G10: 8150 | H10: 9450 | I10: 11200
A11: May Repayments | H11: 6700 | I11: 1150
A12: June Repaymements
A13: July Repayments
A14: Panealries | F14: 600
C15: =SUM(C6:C14) -> 51500 | D15: =SUM(D6:D14) -> 91800 | E15: =SUM(E6:E14) -> 60545 | F15: =SUM(F6:F14) -> 31000 | G15: =SUM(G6:G14) -> 59100 | H15: =SUM(H6:H14) -> 78926.75 | I15: =SUM(I6:I14) -> 61100
C16: =C5-C15 -> 0 | D16: =D5-D15 -> 0 | E16: =E5-E15 -> 0 | F16: =F5-F15 -> 0 | G16: =G5-G15 -> 0 | H16: =H5-H15 -> 0 | I16: =I5-I15 -> 0
